Workbook

Sheet Leia-me
A1: Saúde fiscal do Rio de Janeiro: contas dos estados e dos municípios fluminenses, 2024
A3: O que é esta planilha
A4: Os dados públicos do Siconfi (Tesouro Nacional) usados no projeto, organizados para qualquer pessoa conferir: os valores de entrada, os indicadores calculados por fórmula, as posições do RJ entre os estados, gráficos e a legenda de cada coluna.
A5: Pergunta do projeto: como o Rio de Janeiro e os seus municípios estão gerindo o dinheiro da saúde, e onde as contas públicas estão apertadas?
A7: Como ler
A8: • Texto AZUL = dado que veio da API do Siconfi (entrada). Texto PRETO = fórmula: clique na célula para ver o cálculo.
A9: • Linha azul clara = Rio de Janeiro (o estado, na aba Estados; a capital, na aba Municípios RJ). Linha amarela = dado atípico, mantido e marcado.
A10: • Os indicadores são fórmulas sobre as colunas de entrada, então qualquer número pode ser refeito à mão.
A12: Abas
A13: • Estados: os 27 estados (com o DF), com entradas, indicadores e posições.
A14: • Municípios RJ: os 92 municípios do RJ, com os mesmos campos e a marca dos 12 que entregam relatório simplificado.
A15: • Com e sem: medianas dos municípios com e sem os casos especiais.
... A35: • Dívida e restos a pagar são mostrados de forma descritiva. Nenhuma hipótese foi testada nesta planilha.

Sheet Estados
A1: Ente | B1: Código IBGE | C1: População | D1: Receita realizada (R$) | E1: Despesa empenhada, Anexo 01 (R$) | F1: Despesa total, Anexo 02 (R$) | G1: Despesa em Saúde (R$) | H1: RCL ajustada (R$) | I1: Pessoal Executivo (R$) | J1: Pessoal Legislativo (R$) | K1: Pessoal Judiciário (R$) | L1: Pessoal Ministério Público (R$) | M1: Pessoal Defensoria (R$) | N1: Dívida líquida, % da RCL (declarado) | O1: Limite de dívida do Senado, % da RCL (declarado) | P1: Restos a pagar, saldo (R$) | Q1: Saúde por habitante (R$) | R1: Saúde, % da despesa | S1: Receita por habitante (R$) | T1: Despesa, % da receita | U1: Pessoal total (R$) | V1: Poderes com dado | W1: Pessoal total, % da RCL | X1: Pessoal do Executivo, % da RCL | Y1: Restos a pagar, % da receita | Z1: Posição: saúde por habitante | AA1: Posição: saúde % da despesa | AB1: Posição: despesa % da receita | AC1: Posição: pessoal total % da RCL | AD1: Posição: dívida % da RCL | AE1: Observações
A2: Acre | B2: 12 | C2: 880631 | D2: 1.1345153e+10 | E2: 1.1267054e+10 | F2: 1.1267054e+10 | G2: 2.0842143e+09 | H2: 1.0002459e+10 | I2: 4.6783255e+09 | J2: 1.6852948e+08 | K2: 3.5270476e+08 | L2: 1.6084401e+08 | N2: 0.1977 | O2: 2 | P2: 3.4191512e+08 | Q2: =IFERROR(G2/C2,"") -> 2366.7283 | R2: =IFERROR(G2/F2,"") -> 0.18498307 | S2: =IFERROR(D2/C2,"") -> 12882.982 | T2: =IFERROR(E2/D2,"") -> 0.99311607 | U2: =SUM(I2:M2) -> 5.3604037e+09 | V2: =COUNT(I2:M2) -> 4 | W2: =IFERROR(U2/H2,"") -> 0.53590858 | X2: =IFERROR(I2/H2,"") -> 0.46771752 | Y2: =IF(P2="","",IFERROR(P2/D2,"")) -> 0.030137549 | Z2: =IFERROR(RANK(Q2,Q$2:Q$28),"") -> 2 | AA2: =IFERROR(RANK(R2,R$2:R$28),"") -> 7 | AB2: =IFERROR(RANK(T2,T$2:T$28),"") -> 11 | AC2: =IF(V2>=4,COUNTIFS(V$2:V$28,">=4",W$2:W$28,">"&W2)+1,"n/c") -> 6 | AD2: =IFERROR(RANK(N2,N$2:N$28),"") -> 15
A3: Alagoas | B3: 27 | C3: 3220104 | D3: 1.8945025e+10 | E3: 1.8968613e+10 | F3: 1.8968613e+10 | G3: 3.0459979e+09 | H3: 1.6855657e+10 | I3: 6.0819123e+09 | J3: 1.4055517e+08 | K3: 5.930545e+08 | L3: 2.0633425e+08 | N3: 0.758 | O3: 2 | P3: 1.6246526e+08 | Q3: =IFERROR(G3/C3,"") -> 945.93153 | R3: =IFERROR(G3/F3,"") -> 0.16058095 | S3: =IFERROR(D3/C3,"") -> 5883.3581 | T3: =IFERROR(E3/D3,"") -> 1.0012451 | U3: =SUM(I3:M3) -> 7.0218563e+09 | V3: =COUNT(I3:M3) -> 4 | W3: =IFERROR(U3/H3,"") -> 0.41658752 | X3: =IFERROR(I3/H3,"") -> 0.36082322 | Y3: =IF(P3="","",IFERROR(P3/D3,"")) -> 0.0085756159 | Z3: =IFERROR(RANK(Q3,Q$2:Q$28),"") -> 14 | AA3: =IFERROR(RANK(R3,R$2:R$28),"") -> 15 | AB3: =IFERROR(RANK(T3,T$2:T$28),"") -> 8 | AC3: =IF(V3>=4,COUNTIFS(V$2:V$28,">=4",W$2:W$28,">"&W3)+1,"n/c") -> 25 | AD3: =IFERROR(RANK(N3,N$2:N$28),"") -> 5
A4: Amapá | B4: 16 | C4: 802837 | D4: 1.0447763e+10 | E4: 9.7362929e+09 | F4: 9.7362929e+09 | G4: 2.1406484e+09 | H4: 8.8573935e+09 | I4: 3.8539043e+09 | J4: 59863095 | K4: 4.0956347e+08 | L4: 1.3414572e+08 | N4: -0.0688 | O4: 2 | P4: 5.7330387e+08 | Q4: =IFERROR(G4/C4,"") -> 2666.355 | R4: =IFERROR(G4/F4,"") -> 0.21986278 | S4: =IFERROR(D4/C4,"") -> 13013.555 | T4: =IFERROR(E4/D4,"") -> 0.93190212 | U4: =SUM(I4:M4) -> 4.4574766e+09 | V4: =COUNT(I4:M4) -> 4 | W4: =IFERROR(U4/H4,"") -> 0.50324924 | X4: =IFERROR(I4/H4,"") -> 0.43510591 | Y4: =IF(P4="","",IFERROR(P4/D4,"")) -> 0.054873359 | Z4: =IFERROR(RANK(Q4,Q$2:Q$28),"") -> 1 | AA4: =IFERROR(RANK(R4,R$2:R$28),"") -> 2 | AB4: =IFERROR(RANK(T4,T$2:T$28),"") -> 25 | AC4: =IF(V4>=4,COUNTIFS(V$2:V$28,">=4",W$2:W$28,">"&W4)+1,"n/c") -> 9 | AD4: =IFERROR(RANK(N4,N$2:N$28),"") -> 25
A5: Amazonas | B5: 13 | C5: 4281209 | D5: 3.4299095e+10 | E5: 3.3524115e+10 | F5: 3.3524115e+10 | G5: 5.1655974e+09 | H5: 2.6423983e+10 | I5: 1.0243519e+10 | J5: 3.2768957e+08 | K5: 9.3135511e+08 | L5: 3.2610189e+08 | N5: 0.2968 | O5: 2 | P5: 18596021 | Q5: =IFERROR(G5/C5,"") -> 1206.5745 | R5: =IFERROR(G5/F5,"") -> 0.15408602 | S5: =IFERROR(D5/C5,"") -> 8011.5443 | T5: =IFERROR(E5/D5,"") -> 0.97740521 | U5: =SUM(I5:M5) -> 1.1828666e+10 | V5: =COUNT(I5:M5) -> 4 | W5: =IFERROR(U5/H5,"") -> 0.44764886 | X5: =IFERROR(I5/H5,"") -> 0.38765993 | Y5: =IF(P5="","",IFERROR(P5/D5,"")) -> 0.00054217235 | Z5: =IFERROR(RANK(Q5,Q$2:Q$28),"") -> 9 | AA5: =IFERROR(RANK(R5,R$2:R$28),"") -> 17 | AB5: =IFERROR(RANK(T5,T$2:T$28),"") -> 16 | AC5: =IF(V5>=4,COUNTIFS(V$2:V$28,">=4",W$2:W$28,">"&W5)+1,"n/c") -> 21 | AD5: =IFERROR(RANK(N5,N$2:N$28),"") -> 11
A6: Bahia | B6: 29 | C6: 14850513 | D6: 7.1518231e+10 | E6: 7.141398e+10 | F6: 7.141398e+10 | G6: 1.3792694e+10 | H6: 6.4853816e+10 | I6: 2.7008464e+10 | J6: 2.1041442e+08 | K6: 3.0851095e+09 | L6: 8.7634444e+08 | N6: 0.371 | O6: 2 | P6: 18300343 | Q6: =IFERROR(G6/C6,"") -> 928.76885 | R6: =IFERROR(G6/F6,"") -> 0.19313717 | S6: =IFERROR(D6/C6,"") -> 4815.8762 | T6: =IFERROR(E6/D6,"") -> 0.99854231 | U6: =SUM(I6:M6) -> 3.1180332e+10 | V6: =COUNT(I6:M6) -> 4 | W6: =IFERROR(U6/H6,"") -> 0.48077868 | X6: =IFERROR(I6/H6,"") -> 0.41645142 | Y6: =IF(P6="","",IFERROR(P6/D6,"")) -> 0.00025588361 | Z6: =IFERROR(RANK(Q6,Q$2:Q$28),"") -> 15 | AA6: =IFERROR(RANK(R6,R$2:R$28),"") -> 6 | AB6: =IFERROR(RANK(T6,T$2:T$28),"") -> 10 | AC6: =IF(V6>=4,COUNTIFS(V$2:V$28,">=4",W$2:W$28,">"&W6)+1,"n/c") -> 14 | AD6: =IFERROR(RANK(N6,N$2:N$28),"") -> 8
A7: Ceará | B7: 23 | C7: 9233656 | D7: 3.9438507e+10 | E7: 4.022253e+10 | F7: 4.022253e+10 | G7: 6.9175958e+09 | H7: 3.616444e+10 | I7: 1.5745937e+10 | J7: 2.5024797e+08 | K7: 1.4619188e+09 | L7: 5.5837895e+08 | N7: 0.3306 | O7: 2 | P7: 1.4001215e+08 | Q7: =IFERROR(G7/C7,"") -> 749.17193 | R7: =IFERROR(G7/F7,"") -> 0.17198311 | S7: =IFERROR(D7/C7,"") -> 4271.1691 | T7: =IFERROR(E7/D7,"") -> 1.0198796 | U7: =SUM(I7:M7) -> 1.8016483e+10 | V7: =COUNT(I7:M7) -> 4 | W7: =IFERROR(U7/H7,"") -> 0.49818227 | X7: =IFERROR(I7/H7,"") -> 0.43539834 | Y7: =IF(P7="","",IFERROR(P7/D7,"")) -> 0.0035501382 | Z7: =IFERROR(RANK(Q7,Q$2:Q$28),"") -> 23 | AA7: =IFERROR(RANK(R7,R$2:R$28),"") -> 9 | AB7: =IFERROR(RANK(T7,T$2:T$28),"") -> 4 | AC7: =IF(V7>=4,COUNTIFS(V$2:V$28,">=4",W$2:W$28,">"&W7)+1,"n/c") -> 10 | AD7: =IFERROR(RANK(N7,N$2:N$28),"") -> 9
A8: Distrito Federal | B8: 53 | C8: 2982818 | D8: 3.5629361e+10 | E8: 3.7165148e+10 | F8: 3.7165148e+10 | G8: 5.2288527e+09 | H8: 3.5826653e+10 | I8: 1.4177016e+10 | J8: 5.4345484e+08 | N8: 0.1312 | O8: 2 | P8: 1.4981828e+08 | Q8: =IFERROR(G8/C8,"") -> 1752.9909 | R8: =IFERROR(G8/F8,"") -> 0.14069237 | S8: =IFERROR(D8/C8,"") -> 11944.866 | T8: =IFERROR(E8/D8,"") -> 1.0431045 | U8: =SUM(I8:M8) -> 1.4720471e+10 | V8: =COUNT(I8:M8) -> 2 | W8: =IFERROR(U8/H8,"") -> 0.41088045 | X8: =IFERROR(I8/H8,"") -> 0.39571144 | Y8: =IF(P8="","",IFERROR(P8/D8,"")) -> 0.0042049105 | Z8: =IFERROR(RANK(Q8,Q$2:Q$28),"") -> 5 | AA8: =IFERROR(RANK(R8,R$2:R$28),"") -> 19 | AB8: =IFERROR(RANK(T8,T$2:T$28),"") -> 1 | AC8: =IF(V8>=4,COUNTIFS(V$2:V$28,">=4",W$2:W$28,">"&W8)+1,"n/c") -> n/c | AD8: =IFERROR(RANK(N8,N$2:N$28),"") -> 16 | AE8: Poderes incompletos no RGF: a soma de pessoal fica subestimada
A9: Espírito Santo | B9: 32 | C9: 4102129 | D9: 2.881456e+10 | E9: 2.7810905e+10 | F9: 2.792703e+10 | G9: 5.1573164e+09 | H9: 2.6201081e+10 | I9: 9.4450711e+09 | J9: 2.2908865e+08 | K9: 1.1748009e+09 | L9: 3.9601429e+08 | N9: -0.0976 | O9: 2 | P9: 1.2916622e+08 | Q9: =IFERROR(G9/C9,"") -> 1257.2292 | R9: =IFERROR(G9/F9,"") -> 0.18467114 | S9: =IFERROR(D9/C9,"") -> 7024.294 | T9: =IFERROR(E9/D9,"") -> 0.96516849 | U9: =SUM(I9:M9) -> 1.1244975e+10 | V9: =COUNT(I9:M9) -> 4 | W9: =IFERROR(U9/H9,"") -> 0.4291798 | X9: =IFERROR(I9/H9,"") -> 0.36048402 | Y9: =IF(P9="","",IFERROR(P9/D9,"")) -> 0.004482672 | Z9: =IFERROR(RANK(Q9,Q$2:Q$28),"") -> 8 | AA9: =IFERROR(RANK(R9,R$2:R$28),"") -> 8 | AB9: =IFERROR(RANK(T9,T$2:T$28),"") -> 19 | AC9: =IF(V9>=4,COUNTIFS(V$2:V$28,">=4",W$2:W$28,">"&W9)+1,"n/c") -> 24 | AD9: =IFERROR(RANK(N9,N$2:N$28),"") -> 26
A10: Goiás | B10: 52 | C10: 7350483 | D10: 4.4601992e+10 | E10: 4.2009295e+10 | F10: 4.2009295e+10 | G10: 5.5795966e+09 | H10: 4.223843e+10 | I10: 1.7612043e+10 | J10: 5.5366368e+08 | K10: 2.0660468e+09 | L10: 7.6279786e+08 | N10: 0.2432 | O10: 2 | P10: 5.2124028e+08 | Q10: =IFERROR(G10/C10,"") -> 759.07891 | R10: =IFERROR(G10/F10,"") -> 0.13281815 | S10: =IFERROR(D10/C10,"") -> 6067.8996 | T10: =IFERROR(E10/D10,"") -> 0.94187036 | U10: =SUM(I10:M10) -> 2.0994552e+10 | V10: =COUNT(I10:M10) -> 4 | W10: =IFERROR(U10/H10,"") -> 0.49704858 | X10: =IFERROR(I10/H10,"") -> 0.41696728 | Y10: =IF(P10="","",IFERROR(P10/D10,"")) -> 0.01168648 | Z10: =IFERROR(RANK(Q10,Q$2:Q$28),"") -> 22 | AA10: =IFERROR(RANK(R10,R$2:R$28),"") -> 22 | AB10: =IFERROR(RANK(T10,T$2:T$28),"") -> 24 | AC10: =IF(V10>=4,COUNTIFS(V$2:V$28,">=4",W$2:W$28,">"&W10)+1,"n/c") -> 11 | AD10: =IFERROR(RANK(N10,N$2:N$28),"") -> 14
A11: Maranhão | B11: 21 | C11: 7010960 | D11: 3.112718e+10 | E11: 2.8216423e+10 | F11: 2.8216423e+10 | G11: 4.804534e+09 | H11: 2.9521763e+10 | I11: 9.1632498e+09 | J11: 5.2183411e+08 | K11: 1.3409524e+09 | L11: 5.4658252e+08 | N11: 0.0303 | O11: 2 | P11: 2.1140404e+08 | Q11: =IFERROR(G11/C11,"") -> 685.28904 | R11: =IFERROR(G11/F11,"") -> 0.17027439 | S11: =IFERROR(D11/C11,"") -> 4439.7885 | T11: =IFERROR(E11/D11,"") -> 0.90648824 | U11: =SUM(I11:M11) -> 1.1572619e+10 | V11: =COUNT(I11:M11) -> 4 | W11: =IFERROR(U11/H11,"") -> 0.39200297 | X11: =IFERROR(I11/H11,"") -> 0.31038965 | Y11: =IF(P11="","",IFERROR(P11/D11,"")) -> 0.0067916222 | Z11: =IFERROR(RANK(Q11,Q$2:Q$28),"") -> 24 | AA11: =IFERROR(RANK(R11,R$2:R$28),"") -> 10 | AB11: =IFERROR(RANK(T11,T$2:T$28),"") -> 27 | AC11: =IF(V11>=4,COUNTIFS(V$2:V$28,">=4",W$2:W$28,">"&W11)+1,"n/c") -> 26 | AD11: =IFERROR(RANK(N11,N$2:N$28),"") -> 21
A12: Mato Grosso | B12: 51 | C12: 3836399 | D12: 3.6117368e+10 | E12: 3.6264463e+10 | F12: 3.6264463e+10 | G12: 4.257587e+09 | H12: 3.2886764e+10 | I12: 1.2425266e+10 | J12: 4.3092867e+08 | K12: 1.1715084e+09 | L12: 4.5465088e+08 | N12: -0.1448 | O12: 2 | P12: 3.7132901e+08 | Q12: =IFERROR(G12/C12,"") -> 1109.7873 | R12: =IFERROR(G12/F12,"") -> 0.11740383 | S12: =IFERROR(D12/C12,"") -> 9414.393 | T12: =IFERROR(E12/D12,"") -> 1.0040727 | U12: =SUM(I12:M12) -> 1.4482354e+10 | V12: =COUNT(I12:M12) -> 4 | W12: =IFERROR(U12/H12,"") -> 0.44037031 | X12: =IFERROR(I12/H12,"") -> 0.37781967 | Y12: =IF(P12="","",IFERROR(P12/D12,"")) -> 0.010281176 | Z12: =IFERROR(RANK(Q12,Q$2:Q$28),"") -> 10 | AA12: =IFERROR(RANK(R12,R$2:R$28),"") -> 24 | AB12: =IFERROR(RANK(T12,T$2:T$28),"") -> 6 | AC12: =IF(V12>=4,COUNTIFS(V$2:V$28,">=4",W$2:W$28,">"&W12)+1,"n/c") -> 22 | AD12: =IFERROR(RANK(N12,N$2:N$28),"") -> 27
A13: Mato Grosso do Sul | B13: 50 | C13: 2901895 | D13: 2.2126097e+10 | E13: 2.2929791e+10 | F13: 2.2929791e+10 | G13: 2.6453609e+09 | H13: 2.0253127e+10 | I13: 9.1537189e+09 | J13: 2.1648456e+08 | K13: 1.0369511e+09 | L13: 3.0406547e+08 | N13: 0.2475 | O13: 2.0075992 | P13: 40038019 | Q13: =IFERROR(G13/C13,"") -> 911.59772 | R13: =IFERROR(G13/F13,"") -> 0.11536786 | S13: =IFERROR(D13/C13,"") -> 7624.7061 | T13: =IFERROR(E13/D13,"") -> 1.0363234 | U13: =SUM(I13:M13) -> 1.071122e+10 | V13: =COUNT(I13:M13) -> 4 | W13: =IFERROR(U13/H13,"") -> 0.52886746 | X13: =IFERROR(I13/H13,"") -> 0.4519657 | Y13: =IF(P13="","",IFERROR(P13/D13,"")) -> 0.0018095383 | Z13: =IFERROR(RANK(Q13,Q$2:Q$28),"") -> 17 | AA13: =IFERROR(RANK(R13,R$2:R$28),"") -> 26 | AB13: =IFERROR(RANK(T13,T$2:T$28),"") -> 2 | AC13: =IF(V13>=4,COUNTIFS(V$2:V$28,">=4",W$2:W$28,">"&W13)+1,"n/c") -> 7 | AD13: =IFERROR(RANK(N13,N$2:N$28),"") -> 13
A14: Minas Gerais | B14: 31 | C14: 21322691 | D14: 1.1198721e+11 | E14: 1.0671702e+11 | F14: 1.0671702e+11 | G14: 1.4220754e+10 | H14: 1.0346573e+11 | I14: 5.0492145e+10 | J14: 1.4070978e+09 | K14: 5.6317992e+09 | L14: 1.7855016e+09 | N14: 1.6259 | O14: 2 | P14: 7.4387295e+09 | Q14: =IFERROR(G14/C14,"") -> 666.93055 | R14: =IFERROR(G14/F14,"") -> 0.13325666 | S14: =IFERROR(D14/C14,"") -> 5252.0204 | T14: =IFERROR(E14/D14,"") -> 0.95293939 | U14: =SUM(I14:M14) -> 5.9316544e+10 | V14: =COUNT(I14:M14) -> 4 | W14: =IFERROR(U14/H14,"") -> 0.57329655 | X14: =IFERROR(I14/H14,"") -> 0.48800841 | Y14: =IF(P14="","",IFERROR(P14/D14,"")) -> 0.066424814 | Z14: =IFERROR(RANK(Q14,Q$2:Q$28),"") -> 26 | AA14: =IFERROR(RANK(R14,R$2:R$28),"") -> 20 | AB14: =IFERROR(RANK(T14,T$2:T$28),"") -> 21 | AC14: =IF(V14>=4,COUNTIFS(V$2:V$28,">=4",W$2:W$28,">"&W14)+1,"n/c") -> 2 | AD14: =IFERROR(RANK(N14,N$2:N$28),"") -> 3
A15: Paraná | B15: 41 | C15: 11824665 | D15: 7.0236706e+10 | E15: 6.95202e+10 | F15: 6.9829374e+10 | G15: 9.2825838e+09 | H15: 6.6084617e+10 | I15: 2.8222024e+10 | J15: 5.6151419e+08 | K15: 2.7051506e+09 | L15: 9.9179682e+08 | N15: -0.0507 | O15: 2 | P15: 1.1192007e+09 | Q15: =IFERROR(G15/C15,"") -> 785.01876 | R15: =IFERROR(G15/F15,"") -> 0.13293237 | S15: =IFERROR(D15/C15,"") -> 5939.8474 | T15: =IFERROR(E15/D15,"") -> 0.9897987 | U15: =SUM(I15:M15) -> 3.2480486e+10 | V15: =COUNT(I15:M15) -> 4 | W15: =IFERROR(U15/H15,"") -> 0.49149843 | X15: =IFERROR(I15/H15,"") -> 0.4270589 | Y15: =IF(P15="","",IFERROR(P15/D15,"")) -> 0.015934699 | Z15: =IFERROR(RANK(Q15,Q$2:Q$28),"") -> 20 | AA15: =IFERROR(RANK(R15,R$2:R$28),"") -> 21 | AB15: =IFERROR(RANK(T15,T$2:T$28),"") -> 12 | AC15: =IF(V15>=4,COUNTIFS(V$2:V$28,">=4",W$2:W$28,">"&W15)+1,"n/c") -> 12 | AD15: =IFERROR(RANK(N15,N$2:N$28),"") -> 24
A16: Paraíba | B16: 25 | C16: 4145040 | D16: 2.0348822e+10 | E16: 1.9223056e+10 | F16: 1.9223056e+10 | G16: 3.1731875e+09 | H16: 1.8892083e+10 | I16: 9.1190641e+09 | J16: 3.6325664e+08 | K16: 8.4103274e+08 | L16: 3.2878374e+08 | N16: -0.0237 | O16: 2 | P16: 2.653782e+08 | Q16: =IFERROR(G16/C16,"") -> 765.53845 | R16: =IFERROR(G16/F16,"") -> 0.16507196 | S16: =IFERROR(D16/C16,"") -> 4909.1981 | T16: =IFERROR(E16/D16,"") -> 0.94467659 | U16: =SUM(I16:M16) -> 1.0652137e+10 | V16: =COUNT(I16:M16) -> 4 | W16: =IFERROR(U16/H16,"") -> 0.56384134 | X16: =IFERROR(I16/H16,"") -> 0.48269237 | Y16: =IF(P16="","",IFERROR(P16/D16,"")) -> 0.013041453 | Z16: =IFERROR(RANK(Q16,Q$2:Q$28),"") -> 21 | AA16: =IFERROR(RANK(R16,R$2:R$28),"") -> 11 | AB16: =IFERROR(RANK(T16,T$2:T$28),"") -> 22 | AC16: =IF(V16>=4,COUNTIFS(V$2:V$28,">=4",W$2:W$28,">"&W16)+1,"n/c") -> 3 | AD16: =IFERROR(RANK(N16,N$2:N$28),"") -> 23
A17: Pará | B17: 15 | C17: 8664306 | D17: 4.5431436e+10 | E17: 4.4943282e+10 | F17: 4.4943282e+10 | G17: 5.9044622e+09 | H17: 4.097257e+10 | I17: 1.661552e+10 | J17: 20292474 | K17: 1.5885451e+09 | L17: 6.6081301e+08 | N17: 0.0717 | O17: 2 | P17: 90624091 | Q17: =IFERROR(G17/C17,"") -> 681.46972 | R17: =IFERROR(G17/F17,"") -> 0.13137586 | S17: =IFERROR(D17/C17,"") -> 5243.517 | T17: =IFERROR(E17/D17,"") -> 0.98925515 | U17: =SUM(I17:M17) -> 1.8885171e+10 | V17: =COUNT(I17:M17) -> 4 | W17: =IFERROR(U17/H17,"") -> 0.4609223 | X17: =IFERROR(I17/H17,"") -> 0.4055279 | Y17: =IF(P17="","",IFERROR(P17/D17,"")) -> 0.0019947441 | Z17: =IFERROR(RANK(Q17,Q$2:Q$28),"") -> 25 | AA17: =IFERROR(RANK(R17,R$2:R$28),"") -> 23 | AB17: =IFERROR(RANK(T17,T$2:T$28),"") -> 13 | AC17: =IF(V17>=4,COUNTIFS(V$2:V$28,">=4",W$2:W$28,">"&W17)+1,"n/c") -> 19 | AD17: =IFERROR(RANK(N17,N$2:N$28),"") -> 20
A18: Pernambuco | B18: 26 | C18: 9539029 | D18: 4.6828307e+10 | E18: 4.5920118e+10 | F18: 4.6173592e+10 | G18: 9.6161509e+09 | H18: 4.3773482e+10 | I18: 1.774925e+10 | J18: 5.3213224e+08 | K18: 1.9764011e+09 | L18: 6.5167004e+08 | N18: 0.3007 | O18: 2 | P18: 1.7282965e+08 | Q18: =IFERROR(G18/C18,"") -> 1008.0849 | R18: =IFERROR(G18/F18,"") -> 0.20826084 | S18: =IFERROR(D18/C18,"") -> 4909.1272 | T18: =IFERROR(E18/D18,"") -> 0.98060599 | U18: =SUM(I18:M18) -> 2.0909453e+10 | V18: =COUNT(I18:M18) -> 4 | W18: =IFERROR(U18/H18,"") -> 0.47767398 | X18: =IFERROR(I18/H18,"") -> 0.4054795 | Y18: =IF(P18="","",IFERROR(P18/D18,"")) -> 0.0036907088 | Z18: =IFERROR(RANK(Q18,Q$2:Q$28),"") -> 11 | AA18: =IFERROR(RANK(R18,R$2:R$28),"") -> 3 | AB18: =IFERROR(RANK(T18,T$2:T$28),"") -> 15 | AC18: =IF(V18>=4,COUNTIFS(V$2:V$28,">=4",W$2:W$28,">"&W18)+1,"n/c") -> 15 | AD18: =IFERROR(RANK(N18,N$2:N$28),"") -> 10
A19: Piauí | B19: 22 | C19: 3375646 | D19: 2.0493869e+10 | E19: 2.0903832e+10 | F19: 2.0903832e+10 | G19: 3.3839217e+09 | H19: 1.7101669e+10 | I19: 7.1244165e+09 | J19: 3.5564783e+08 | K19: 6.540822e+08 | L19: 2.2415717e+08 | N19: 0.6272 | O19: 2.0044339 | P19: 4.8462745e+08 | Q19: =IFERROR(G19/C19,"") -> 1002.4516 | R19: =IFERROR(G19/F19,"") -> 0.16188045 | S19: =IFERROR(D19/C19,"") -> 6071.0953 | T19: =IFERROR(E19/D19,"") -> 1.0200042 | U19: =SUM(I19:M19) -> 8.3583037e+09 | V19: =COUNT(I19:M19) -> 4 | W19: =IFERROR(U19/H19,"") -> 0.48874198 | X19: =IFERROR(I19/H19,"") -> 0.41659188 | Y19: =IF(P19="","",IFERROR(P19/D19,"")) -> 0.023647436 | Z19: =IFERROR(RANK(Q19,Q$2:Q$28),"") -> 12 | AA19: =IFERROR(RANK(R19,R$2:R$28),"") -> 14 | AB19: =IFERROR(RANK(T19,T$2:T$28),"") -> 3 | AC19: =IF(V19>=4,COUNTIFS(V$2:V$28,">=4",W$2:W$28,">"&W19)+1,"n/c") -> 13 | AD19: =IFERROR(RANK(N19,N$2:N$28),"") -> 6
A20: Rio Grande do Norte | B20: 24 | C20: 3446071 | D20: 1.9085896e+10 | E20: 1.914144e+10 | F20: 1.914144e+10 | G20: 2.7827682e+09 | H20: 1.723304e+10 | I20: 9.9197479e+09 | J20: 3.6939127e+08 | K20: 8.9580453e+08 | L20: 2.9870643e+08 | N20: 0.4018 | O20: 2 | P20: 3.1844703e+08 | Q20: =IFERROR(G20/C20,"") -> 807.51911 | R20: =IFERROR(G20/F20,"") -> 0.14537925 | S20: =IFERROR(D20/C20,"") -> 5538.4512 | T20: =IFERROR(E20/D20,"") -> 1.0029102 | U20: =SUM(I20:M20) -> 1.148365e+10 | V20: =COUNT(I20:M20) -> 4 | W20: =IFERROR(U20/H20,"") -> 0.66637402 | X20: =IFERROR(I20/H20,"") -> 0.5756238 | Y20: =IF(P20="","",IFERROR(P20/D20,"")) -> 0.01668494 | Z20: =IFERROR(RANK(Q20,Q$2:Q$28),"") -> 19 | AA20: =IFERROR(RANK(R20,R$2:R$28),"") -> 18 | AB20: =IFERROR(RANK(T20,T$2:T$28),"") -> 7 | AC20: =IF(V20>=4,COUNTIFS(V$2:V$28,">=4",W$2:W$28,">"&W20)+1,"n/c") -> 1 | AD20: =IFERROR(RANK(N20,N$2:N$28),"") -> 7
... A23: Rondônia | B23: 11 | C23: 1746227 | D23: 1.5071357e+10 | E23: 1.4446047e+10 | F23: 1.4526983e+10 | G23: 2.3653521e+09 | H23: 1.4190334e+10 | I23: 5.3082218e+09 | J23: 2.2024795e+08 | K23: 6.8511477e+08 | L23: 1.9192673e+08 | N23: -0.0134 | O23: 2 | P23: 1.3156443e+08 | Q23: =IFERROR(G23/C23,"") -> 1354.5502 | R23: =IFERROR(G23/F23,"") -> 0.16282473 | S23: =IFERROR(D23/C23,"") -> 8630.812 | T23: =IFERROR(E23/D23,"") -> 0.95851002 | U23: =SUM(I23:M23) -> 6.4055112e+09 | V23: =COUNT(I23:M23) -> 4 | W23: =IFERROR(U23/H23,"") -> 0.45139959 | X23: =IFERROR(I23/H23,"") -> 0.37407306 | Y23: =IF(P23="","",IFERROR(P23/D23,"")) -> 0.0087294352 | Z23: =IFERROR(RANK(Q23,Q$2:Q$28),"") -> 6 | AA23: =IFERROR(RANK(R23,R$2:R$28),"") -> 13 | AB23: =IFERROR(RANK(T23,T$2:T$28),"") -> 20 | AC23: =IF(V23>=4,COUNTIFS(V$2:V$28,">=4",W$2:W$28,">"&W23)+1,"n/c") -> 20 | AD23: =IFERROR(RANK(N23,N$2:N$28),"") -> 22
A24: Roraima | B24: 14 | C24: 716793 | D24: 8.6099317e+09 | E24: 8.1287938e+09 | F24: 8.1288364e+09 | G24: 1.6066477e+09 | H24: 7.746996e+09 | I24: 3.6623856e+09 | J24: 1.6530731e+08 | K24: 3.0559074e+08 | L24: 97411417 | N24: 0.1002 | O24: 0.90262662 | P24: 1.0515423e+08 | Q24: =IFERROR(G24/C24,"") -> 2241.4389 | R24: =IFERROR(G24/F24,"") -> 0.19764793 | S24: =IFERROR(D24/C24,"") -> 12011.741 | T24: =IFERROR(E24/D24,"") -> 0.94411827 | U24: =SUM(I24:M24) -> 4.230695e+09 | V24: =COUNT(I24:M24) -> 4 | W24: =IFERROR(U24/H24,"") -> 0.54610781 | X24: =IFERROR(I24/H24,"") -> 0.47274912 | Y24: =IF(P24="","",IFERROR(P24/D24,"")) -> 0.012213132 | Z24: =IFERROR(RANK(Q24,Q$2:Q$28),"") -> 4 | AA24: =IFERROR(RANK(R24,R$2:R$28),"") -> 5 | AB24: =IFERROR(RANK(T24,T$2:T$28),"") -> 23 | AC24: =IF(V24>=4,COUNTIFS(V$2:V$28,">=4",W$2:W$28,">"&W24)+1,"n/c") -> 4 | AD24: =IFERROR(RANK(N24,N$2:N$28),"") -> 19 | AE24: Limite de dívida declarado fora do padrão (a checar)
A25: Santa Catarina | B25: 42 | C25: 8058441 | D25: 4.9164304e+10 | E25: 4.7523185e+10 | F25: 4.7523185e+10 | G25: 7.794192e+09 | H25: 4.6437402e+10 | I25: 1.8419359e+10 | J25: 6.2086819e+08 | K25: 2.19721e+09 | L25: 6.9480149e+08 | N25: 0.2836 | O25: 2 | P25: 3415309.6 | Q25: =IFERROR(G25/C25,"") -> 967.20842 | R25: =IFERROR(G25/F25,"") -> 0.1640082 | S25: =IFERROR(D25/C25,"") -> 6100.9696 | T25: =IFERROR(E25/D25,"") -> 0.96661972 | U25: =SUM(I25:M25) -> 2.1932238e+10 | V25: =COUNT(I25:M25) -> 4 | W25: =IFERROR(U25/H25,"") -> 0.47229684 | X25: =IFERROR(I25/H25,"") -> 0.39664921 | Y25: =IF(P25="","",IFERROR(P25/D25,"")) -> 6.9467263e-05 | Z25: =IFERROR(RANK(Q25,Q$2:Q$28),"") -> 13 | AA25: =IFERROR(RANK(R25,R$2:R$28),"") -> 12 | AB25: =IFERROR(RANK(T25,T$2:T$28),"") -> 18 | AC25: =IF(V25>=4,COUNTIFS(V$2:V$28,">=4",W$2:W$28,">"&W25)+1,"n/c") -> 16 | AD25: =IFERROR(RANK(N25,N$2:N$28),"") -> 12
A26: Sergipe | B26: 28 | C26: 2291077 | D26: 1.6129987e+10 | E26: 1.4885366e+10 | F26: 1.4885366e+10 | G26: 2.9719701e+09 | H26: 1.5169854e+10 | I26: 6.1240284e+09 | J26: 1.3805253e+08 | K26: 6.6339594e+08 | L26: 1.8728907e+08 | N26: 0.1156 | O26: 2 | P26: 32878637 | Q26: =IFERROR(G26/C26,"") -> 1297.1935 | R26: =IFERROR(G26/F26,"") -> 0.19965718 | S26: =IFERROR(D26/C26,"") -> 7040.3513 | T26: =IFERROR(E26/D26,"") -> 0.92283804 | U26: =SUM(I26:M26) -> 7.112766e+09 | V26: =COUNT(I26:M26) -> 4 | W26: =IFERROR(U26/H26,"") -> 0.46887503 | X26: =IFERROR(I26/H26,"") -> 0.40369725 | Y26: =IF(P26="","",IFERROR(P26/D26,"")) -> 0.0020383549 | Z26: =IFERROR(RANK(Q26,Q$2:Q$28),"") -> 7 | AA26: =IFERROR(RANK(R26,R$2:R$28),"") -> 4 | AB26: =IFERROR(RANK(T26,T$2:T$28),"") -> 26 | AC26: =IF(V26>=4,COUNTIFS(V$2:V$28,">=4",W$2:W$28,">"&W26)+1,"n/c") -> 17 | AD26: =IFERROR(RANK(N26,N$2:N$28),"") -> 17
A27: São Paulo | B27: 35 | C27: 45973194 | D27: 3.5400969e+11 | E27: 3.4572484e+11 | F27: 3.4572484e+11 | G27: 4.0427024e+10 | H27: 2.5079391e+11 | I27: 1.0581155e+11 | J27: 9.5582255e+08 | K27: 79717785 | L27: 3.2226456e+09 | N27: 1.2655 | O27: 2 | P27: 3.3142102e+09 | Q27: =IFERROR(G27/C27,"") -> 879.36078 | R27: =IFERROR(G27/F27,"") -> 0.1169341 | S27: =IFERROR(D27/C27,"") -> 7700.3501 | T27: =IFERROR(E27/D27,"") -> 0.9765971 | U27: =SUM(I27:M27) -> 1.1006973e+11 | V27: =COUNT(I27:M27) -> 4 | W27: =IFERROR(U27/H27,"") -> 0.4388852 | X27: =IFERROR(I27/H27,"") -> 0.42190637 | Y27: =IF(P27="","",IFERROR(P27/D27,"")) -> 0.0093619194 | Z27: =IFERROR(RANK(Q27,Q$2:Q$28),"") -> 18 | AA27: =IFERROR(RANK(R27,R$2:R$28),"") -> 25 | AB27: =IFERROR(RANK(T27,T$2:T$28),"") -> 17 | AC27: =IF(V27>=4,COUNTIFS(V$2:V$28,">=4",W$2:W$28,">"&W27)+1,"n/c") -> 23 | AD27: =IFERROR(RANK(N27,N$2:N$28),"") -> 4
A28: Tocantins | B28: 17 | C28: 1577342 | D28: 1.6299319e+10 | E28: 1.6285356e+10 | F28: 1.6285356e+10 | G28: 3.6261016e+09 | H28: 1.4600906e+10 | I28: 6.7626333e+09 | J28: 1.526274e+08 | K28: 5.7551129e+08 | L28: 1.8811172e+08 | N28: 0.1092 | O28: 2 | P28: 3.1980411e+08 | Q28: =IFERROR(G28/C28,"") -> 2298.8683 | R28: =IFERROR(G28/F28,"") -> 0.22266026 | S28: =IFERROR(D28/C28,"") -> 10333.409 | T28: =IFERROR(E28/D28,"") -> 0.99914333 | U28: =SUM(I28:M28) -> 7.6788837e+09 | V28: =COUNT(I28:M28) -> 4 | W28: =IFERROR(U28/H28,"") -> 0.52591829 | X28: =IFERROR(I28/H28,"") -> 0.46316531 | Y28: =IF(P28="","",IFERROR(P28/D28,"")) -> 0.019620704 | Z28: =IFERROR(RANK(Q28,Q$2:Q$28),"") -> 3 | AA28: =IFERROR(RANK(R28,R$2:R$28),"") -> 1 | AB28: =IFERROR(RANK(T28,T$2:T$28),"") -> 9 | AC28: =IF(V28>=4,COUNTIFS(V$2:V$28,">=4",W$2:W$28,">"&W28)+1,"n/c") -> 8 | AD28: =IFERROR(RANK(N28,N$2:N$28),"") -> 18

Sheet Municípios RJ
A1: Ente | B1: Código IBGE | C1: População | D1: Receita realizada (R$) | E1: Despesa empenhada, Anexo 01 (R$) | F1: Despesa total, Anexo 02 (R$) | G1: Despesa em Saúde (R$) | H1: RCL ajustada (R$) | I1: Pessoal Executivo (R$) | J1: Pessoal Legislativo (R$) | K1: Dívida líquida, % da RCL (declarado) | L1: Limite de dívida do Senado, % da RCL (declarado) | M1: Restos a pagar, saldo (R$) | N1: Relatório simplificado? | O1: Caso especial | P1: Saúde por habitante (R$) | Q1: Saúde, % da despesa | R1: Receita por habitante (R$) | S1: Despesa, % da receita | T1: Pessoal total (R$) | U1: Poderes com dado | V1: Pessoal total, % da RCL | W1: Pessoal do Executivo, % da RCL | X1: Restos a pagar, % da receita | Y1: Posição: saúde por habitante | Z1: Posição: saúde % da despesa | AA1: Posição: despesa % da receita | AB1: Posição: pessoal total % da RCL | AC1: Observações
A2: Angra dos Reis | B2: 3300100 | C2: 179120 | D2: 2.3367137e+09 | E2: 2.6567244e+09 | F2: 2.6567244e+09 | G2: 6.7932835e+08 | H2: 2.0798704e+09 | I2: 9.1124773e+08 | J2: 45377108 | K2: -0.1644 | L2: 1.2 | M2: 9009662.6 | N2: não | P2: =IFERROR(G2/C2,"") -> 3792.5879 | Q2: =IFERROR(G2/F2,"") -> 0.25570148 | R2: =IFERROR(D2/C2,"") -> 13045.521 | S2: =IFERROR(E2/D2,"") -> 1.136949 | T2: =SUM(I2:J2) -> 9.5662484e+08 | U2: =COUNT(I2:J2) -> 2 | V2: =IFERROR(T2/H2,"") -> 0.45994444 | W2: =IFERROR(I2/H2,"") -> 0.43812717 | X2: =IF(M2="","",IFERROR(M2/D2,"")) -> 0.003855698 | Y2: =IFERROR(RANK(P2,P$2:P$93),"") -> 12 | Z2: =IFERROR(RANK(Q2,Q$2:Q$93),"") -> 66 | AA2: =IFERROR(RANK(S2,S$2:S$93),"") -> 8 | AB2: =IF(U2>=2,COUNTIFS(U$2:U$93,">=2",V$2:V$93,">"&V2)+1,"n/c") -> 51
A3: Aperibé | B3: 3300159 | C3: 11420 | D3: 1.1869905e+08 | E3: 1.1102717e+08 | F3: 1.1102717e+08 | G3: 34661348 | H3: 94802416 | I3: 47311944 | J3: 2610995.9 | K3: 0.0715 | L3: 1.2 | M3: 663931.38 | N3: não | P3: =IFERROR(G3/C3,"") -> 3035.1443 | Q3: =IFERROR(G3/F3,"") -> 0.31218798 | R3: =IFERROR(D3/C3,"") -> 10393.962 | S3: =IFERROR(E3/D3,"") -> 0.93536698 | T3: =SUM(I3:J3) -> 49922940 | U3: =COUNT(I3:J3) -> 2 | V3: =IFERROR(T3/H3,"") -> 0.52659987 | W3: =IFERROR(I3/H3,"") -> 0.49905842 | X3: =IF(M3="","",IFERROR(M3/D3,"")) -> 0.0055934011 | Y3: =IFERROR(RANK(P3,P$2:P$93),"") -> 30 | Z3: =IFERROR(RANK(Q3,Q$2:Q$93),"") -> 30 | AA3: =IFERROR(RANK(S3,S$2:S$93),"") -> 82 | AB3: =IF(U3>=2,COUNTIFS(U$2:U$93,">=2",V$2:V$93,">"&V3)+1,"n/c") -> 24
A4: Araruama | B4: 3300209 | C4: 137773 | D4: 1.1574741e+09 | E4: 1.1837809e+09 | F4: 1.1837809e+09 | G4: 2.7002151e+08 | H4: 1.121422e+09 | I4: 3.8675392e+08 | J4: 13680510 | K4: -0.041 | L4: 1.2 | M4: 28070875 | N4: não | P4: =IFERROR(G4/C4,"") -> 1959.9015 | Q4: =IFERROR(G4/F4,"") -> 0.22810092 | R4: =IFERROR(D4/C4,"") -> 8401.3133 | S4: =IFERROR(E4/D4,"") -> 1.0227277 | T4: =SUM(I4:J4) -> 4.0043443e+08 | U4: =COUNT(I4:J4) -> 2 | V4: =IFERROR(T4/H4,"") -> 0.35707737 | W4: =IFERROR(I4/H4,"") -> 0.34487812 | X4: =IF(M4="","",IFERROR(M4/D4,"")) -> 0.024251838 | Y4: =IFERROR(RANK(P4,P$2:P$93),"") -> 63 | Z4: =IFERROR(RANK(Q4,Q$2:Q$93),"") -> 82 | AA4: =IFERROR(RANK(S4,S$2:S$93),"") -> 45 | AB4: =IF(U4>=2,COUNTIFS(U$2:U$93,">=2",V$2:V$93,">"&V4)+1,"n/c") -> 83
A5: Areal | B5: 3300225 | C5: 12236 | D5: 1.4418504e+08 | E5: 1.4874369e+08 | F5: 1.4874369e+08 | G5: 34690389 | H5: 44840732 | I5: 69129369 | J5: 2493716.5 | K5: -0.3649 | L5: 1.2 | M5: 8934648.3 | N5: não | O5: RCL atípica | P5: =IFERROR(G5/C5,"") -> 2835.1086 | Q5: =IFERROR(G5/F5,"") -> 0.23322259 | R5: =IFERROR(D5/C5,"") -> 11783.674 | S5: =IFERROR(E5/D5,"") -> 1.0316167 | T5: =SUM(I5:J5) -> 71623085 | U5: =COUNT(I5:J5) -> 2 | V5: =IFERROR(T5/H5,"") -> 1.5972773 | W5: =IFERROR(I5/H5,"") -> 1.5416646 | X5: =IF(M5="","",IFERROR(M5/D5,"")) -> 0.061966543 | Y5: =IFERROR(RANK(P5,P$2:P$93),"") -> 32 | Z5: =IFERROR(RANK(Q5,Q$2:Q$93),"") -> 79 | AA5: =IFERROR(RANK(S5,S$2:S$93),"") -> 42 | AB5: =IF(U5>=2,COUNTIFS(U$2:U$93,">=2",V$2:V$93,">"&V5)+1,"n/c") -> 1 | AC5: Rcl atípica
A6: Armação dos Búzios | B6: 3300233 | C6: 42442 | D6: 6.3243421e+08 | E6: 5.426639e+08 | F6: 5.426639e+08 | G6: 1.5623752e+08 | H6: 5.5601532e+08 | I6: 2.6154529e+08 | J6: 9880449.4 | K6: -0.1321 | L6: 1.2 | M6: 4828202.3 | N6: não | O6: totais de despesa inconsistentes | P6: =IFERROR(G6/C6,"") -> 3681.2006 | Q6: =IFERROR(G6/F6,"") -> 0.28790844 | R6: =IFERROR(D6/C6,"") -> 14901.141 | S6: =IFERROR(E6/D6,"") -> 0.85805589 | T6: =SUM(I6:J6) -> 2.7142574e+08 | U6: =COUNT(I6:J6) -> 2 | V6: =IFERROR(T6/H6,"") -> 0.48816235 | W6: =IFERROR(I6/H6,"") -> 0.47039225 | X6: =IF(M6="","",IFERROR(M6/D6,"")) -> 0.0076343154 | Y6: =IFERROR(RANK(P6,P$2:P$93),"") -> 16 | Z6: =IFERROR(RANK(Q6,Q$2:Q$93),"") -> 48 | AA6: =IFERROR(RANK(S6,S$2:S$93),"") -> 90 | AB6: =IF(U6>=2,COUNTIFS(U$2:U$93,">=2",V$2:V$93,">"&V6)+1,"n/c") -> 44 | AC6: Totais de despesa inconsistentes
A7: Arraial do Cabo | B7: 3300258 | C7: 32794 | D7: 8.1886509e+08 | E7: 7.1678302e+08 | F7: 7.1678302e+08 | G7: 1.8117219e+08 | H7: 8.0508738e+08 | I7: 3.3095475e+08 | J7: 5818675.8 | K7: -0.1844 | L7: 1.2 | M7: 8965622.9 | N7: não | P7: =IFERROR(G7/C7,"") -> 5524.553 | Q7: =IFERROR(G7/F7,"") -> 0.25275737 | R7: =IFERROR(D7/C7,"") -> 24969.967 | S7: =IFERROR(E7/D7,"") -> 0.87533714 | T7: =SUM(I7:J7) -> 3.3677343e+08 | U7: =COUNT(I7:J7) -> 2 | V7: =IFERROR(T7/H7,"") -> 0.41830668 | W7: =IFERROR(I7/H7,"") -> 0.41107929 | X7: =IF(M7="","",IFERROR(M7/D7,"")) -> 0.01094884 | Y7: =IFERROR(RANK(P7,P$2:P$93),"") -> 3 | Z7: =IFERROR(RANK(Q7,Q$2:Q$93),"") -> 67 | AA7: =IFERROR(RANK(S7,S$2:S$93),"") -> 89 | AB7: =IF(U7>=2,COUNTIFS(U$2:U$93,">=2",V$2:V$93,">"&V7)+1,"n/c") -> 70
A8: Barra Mansa | B8: 3300407 | C8: 181688 | D8: 8.975346e+08 | E8: 9.3671934e+08 | F8: 9.3671934e+08 | G8: 2.5825053e+08 | H8: 8.4582985e+08 | I8: 4.081326e+08 | J8: 17012906 | K8: -0.0047 | L8: 1.2000049 | M8: 3363404.2 | N8: não | P8: =IFERROR(G8/C8,"") -> 1421.3956 | Q8: =IFERROR(G8/F8,"") -> 0.27569681 | R8: =IFERROR(D8/C8,"") -> 4939.9773 | S8: =IFERROR(E8/D8,"") -> 1.0436582 | T8: =SUM(I8:J8) -> 4.2514551e+08 | U8: =COUNT(I8:J8) -> 2 | V8: =IFERROR(T8/H8,"") -> 0.50263715 | W8: =IFERROR(I8/H8,"") -> 0.48252329 | X8: =IF(M8="","",IFERROR(M8/D8,"")) -> 0.0037473811 | Y8: =IFERROR(RANK(P8,P$2:P$93),"") -> 78 | Z8: =IFERROR(RANK(Q8,Q$2:Q$93),"") -> 53 | AA8: =IFERROR(RANK(S8,S$2:S$93),"") -> 36 | AB8: =IF(U8>=2,COUNTIFS(U$2:U$93,">=2",V$2:V$93,">"&V8)+1,"n/c") -> 36
A9: Barra do Piraí | B9: 3300308 | C9: 98501 | D9: 4.1355392e+08 | E9: 5.0483706e+08 | F9: 5.0483706e+08 | G9: 1.2548746e+08 | H9: 3.9585106e+08 | I9: 1.7364841e+08 | J9: 6018476.3 | K9: 0.2723 | L9: 1.2 | M9: 84231412 | N9: não | P9: =IFERROR(G9/C9,"") -> 1273.9714 | Q9: =IFERROR(G9/F9,"") -> 0.24857022 | R9: =IFERROR(D9/C9,"") -> 4198.4743 | S9: =IFERROR(E9/D9,"") -> 1.2207285 | T9: =SUM(I9:J9) -> 1.7966688e+08 | U9: =COUNT(I9:J9) -> 2 | V9: =IFERROR(T9/H9,"") -> 0.45387495 | W9: =IFERROR(I9/H9,"") -> 0.43867106 | X9: =IF(M9="","",IFERROR(M9/D9,"")) -> 0.20367698 | Y9: =IFERROR(RANK(P9,P$2:P$93),"") -> 81 | Z9: =IFERROR(RANK(Q9,Q$2:Q$93),"") -> 71 | AA9: =IFERROR(RANK(S9,S$2:S$93),"") -> 4 | AB9: =IF(U9>=2,COUNTIFS(U$2:U$93,">=2",V$2:V$93,">"&V9)+1,"n/c") -> 55
A10: Belford Roxo | B10: 3300456 | C10: 518263 | D10: 1634765364 | E10: 1.6801743e+09 | F10: 1.6801743e+09 | G10: 5.7094849e+08 | H10: 1.4603238e+09 | I10: 7.2950242e+08 | J10: 17054048 | K10: 0.471 | L10: 1.2 | M10: 1.8647834e+08 | N10: não | P10: =IFERROR(G10/C10,"") -> 1101.6578 | Q10: =IFERROR(G10/F10,"") -> 0.33981502 | R10: =IFERROR(D10/C10,"") -> 3154.3162 | S10: =IFERROR(E10/D10,"") -> 1.0277771 | T10: =SUM(I10:J10) -> 7.4655646e+08 | U10: =COUNT(I10:J10) -> 2 | V10: =IFERROR(T10/H10,"") -> 0.51122668 | W10: =IFERROR(I10/H10,"") -> 0.49954841 | X10: =IF(M10="","",IFERROR(M10/D10,"")) -> 0.1140704 | Y10: =IFERROR(RANK(P10,P$2:P$93),"") -> 87 | Z10: =IFERROR(RANK(Q10,Q$2:Q$93),"") -> 17 | AA10: =IFERROR(RANK(S10,S$2:S$93),"") -> 43 | AB10: =IF(U10>=2,COUNTIFS(U$2:U$93,">=2",V$2:V$93,">"&V10)+1,"n/c") -> 33 | AC10: Limite de dívida declarado já como percentual
A11: Bom Jardim | B11: 3300506 | C11: 29736 | D11: 1.6387911e+08 | E11: 1.5335928e+08 | F11: 1.5335928e+08 | G11: 43970483 | H11: 1.2607264e+08 | I11: 61522670 | J11: 3969569 | K11: -0.1417 | L11: 1.2 | M11: 1776388.7 | N11: não | P11: =IFERROR(G11/C11,"") -> 1478.6953 | Q11: =IFERROR(G11/F11,"") -> 0.2867155 | R11: =IFERROR(D11/C11,"") -> 5511.1349 | S11: =IFERROR(E11/D11,"") -> 0.93580741 | T11: =SUM(I11:J11) -> 65492239 | U11: =COUNT(I11:J11) -> 2 | V11: =IFERROR(T11/H11,"") -> 0.51948019 | W11: =IFERROR(I11/H11,"") -> 0.48799382 | X11: =IF(M11="","",IFERROR(M11/D11,"")) -> 0.010839629 | Y11: =IFERROR(RANK(P11,P$2:P$93),"") -> 76 | Z11: =IFERROR(RANK(Q11,Q$2:Q$93),"") -> 49 | AA11: =IFERROR(RANK(S11,S$2:S$93),"") -> 81 | AB11: =IF(U11>=2,COUNTIFS(U$2:U$93,">=2",V$2:V$93,">"&V11)+1,"n/c") -> 27
A12: Bom Jesus do Itabapoana | B12: 3300605 | C12: 37172 | D12: 2.8219033e+08 | E12: 2.9488593e+08 | F12: 2.9488593e+08 | G12: 1.4129504e+08 | H12: 2.4664195e+08 | I12: 80617197 | J12: 4625225.2 | K12: 0.1611 | L12: 1.2 | M12: 2202369.9 | N12: não | P12: =IFERROR(G12/C12,"") -> 3801.1149 | Q12: =IFERROR(G12/F12,"") -> 0.47915152 | R12: =IFERROR(D12/C12,"") -> 7591.4756 | S12: =IFERROR(E12/D12,"") -> 1.0449895 | T12: =SUM(I12:J12) -> 85242423 | U12: =COUNT(I12:J12) -> 2 | V12: =IFERROR(T12/H12,"") -> 0.34561202 | W12: =IFERROR(I12/H12,"") -> 0.32685923 | X12: =IF(M12="","",IFERROR(M12/D12,"")) -> 0.0078045546 | Y12: =IFERROR(RANK(P12,P$2:P$93),"") -> 11 | Z12: =IFERROR(RANK(Q12,Q$2:Q$93),"") -> 1 | AA12: =IFERROR(RANK(S12,S$2:S$93),"") -> 33 | AB12: =IF(U12>=2,COUNTIFS(U$2:U$93,">=2",V$2:V$93,">"&V12)+1,"n/c") -> 84
A13: Cabo Frio | B13: 3300704 | C13: 238166 | D13: 1.4712842e+09 | E13: 1.5653301e+09 | F13: 1.5653301e+09 | G13: 4.7316677e+08 | H13: 1.4227707e+09 | I13: 9.0017406e+08 | J13: 11425953 | K13: 0.6179 | L13: 1.2 | M13: 87105068 | N13: não | P13: =IFERROR(G13/C13,"") -> 1986.71 | Q13: =IFERROR(G13/F13,"") -> 0.30227923 | R13: =IFERROR(D13/C13,"") -> 6177.5575 | S13: =IFERROR(E13/D13,"") -> 1.063921 | T13: =SUM(I13:J13) -> 9.1160001e+08 | U13: =COUNT(I13:J13) -> 2 | V13: =IFERROR(T13/H13,"") -> 0.64072167 | W13: =IFERROR(I13/H13,"") -> 0.6326909 | X13: =IF(M13="","",IFERROR(M13/D13,"")) -> 0.059203429 | Y13: =IFERROR(RANK(P13,P$2:P$93),"") -> 60 | Z13: =IFERROR(RANK(Q13,Q$2:Q$93),"") -> 39 | AA13: =IFERROR(RANK(S13,S$2:S$93),"") -> 26 | AB13: =IF(U13>=2,COUNTIFS(U$2:U$93,">=2",V$2:V$93,">"&V13)+1,"n/c") -> 4
A14: Cachoeiras de Macacu | B14: 3300803 | C14: 59837 | D14: 4.6063089e+08 | E14: 4.9834422e+08 | F14: 4.9834422e+08 | G14: 1.596082e+08 | H14: 4.4617769e+08 | I14: 1.5308225e+08 | J14: 8157546.4 | K14: -0.1487 | L14: 1.2 | M14: 9435774.7 | N14: não | P14: =IFERROR(G14/C14,"") -> 2667.383 | Q14: =IFERROR(G14/F14,"") -> 0.32027701 | R14: =IFERROR(D14/C14,"") -> 7698.0947 | S14: =IFERROR(E14/D14,"") -> 1.0818732 | T14: =SUM(I14:J14) -> 1.612398e+08 | U14: =COUNT(I14:J14) -> 2 | V14: =IFERROR(T14/H14,"") -> 0.36138023 | W14: =IFERROR(I14/H14,"") -> 0.34309705 | X14: =IF(M14="","",IFERROR(M14/D14,"")) -> 0.020484459 | Y14: =IFERROR(RANK(P14,P$2:P$93),"") -> 37 | Z14: =IFERROR(RANK(Q14,Q$2:Q$93),"") -> 25 | AA14: =IFERROR(RANK(S14,S$2:S$93),"") -> 18 | AB14: =IF(U14>=2,COUNTIFS(U$2:U$93,">=2",V$2:V$93,">"&V14)+1,"n/c") -> 81
A15: Cambuci | B15: 3300902 | C15: 15070 | D15: 1.2365993e+08 | E15: 1.5102724e+08 | F15: 1.5102724e+08 | G15: 49074793 | H15: 1.151191e+08 | I15: 59102317 | J15: 2100931.2 | K15: -0.3379 | L15: 1.2 | M15: 3069704.7 | N15: não | P15: =IFERROR(G15/C15,"") -> 3256.4561 | Q15: =IFERROR(G15/F15,"") -> 0.32494 | R15: =IFERROR(D15/C15,"") -> 8205.7019 | S15: =IFERROR(E15/D15,"") -> 1.2213111 | T15: =SUM(I15:J15) -> 61203248 | U15: =COUNT(I15:J15) -> 2 | V15: =IFERROR(T15/H15,"") -> 0.53165154 | W15: =IFERROR(I15/H15,"") -> 0.51340148 | X15: =IF(M15="","",IFERROR(M15/D15,"")) -> 0.024823763 | Y15: =IFERROR(RANK(P15,P$2:P$93),"") -> 23 | Z15: =IFERROR(RANK(Q15,Q$2:Q$93),"") -> 24 | AA15: =IFERROR(RANK(S15,S$2:S$93),"") -> 3 | AB15: =IF(U15>=2,COUNTIFS(U$2:U$93,">=2",V$2:V$93,">"&V15)+1,"n/c") -> 21
A16: Campos dos Goytacazes | B16: 3301009 | C16: 519011 | D16: 2.8496695e+09 | E16: 3.0752154e+09 | F16: 3.0752154e+09 | G16: 1.1483046e+09 | H16: 2.6305362e+09 | I16: 1.1228287e+09 | J16: 31510616 | K16: 0.2149 | L16: 1.2 | M16: 7257598.7 | N16: não | P16: =IFERROR(G16/C16,"") -> 2212.486 | Q16: =IFERROR(G16/F16,"") -> 0.37340623 | R16: =IFERROR(D16/C16,"") -> 5490.5764 | S16: =IFERROR(E16/D16,"") -> 1.0791481 | T16: =SUM(I16:J16) -> 1.1543393e+09 | U16: =COUNT(I16:J16) -> 2 | V16: =IFERROR(T16/H16,"") -> 0.43882284 | W16: =IFERROR(I16/H16,"") -> 0.42684406 | X16: =IF(M16="","",IFERROR(M16/D16,"")) -> 0.0025468212 | Y16: =IFERROR(RANK(P16,P$2:P$93),"") -> 51 | Z16: =IFERROR(RANK(Q16,Q$2:Q$93),"") -> 6 | AA16: =IFERROR(RANK(S16,S$2:S$93),"") -> 20 | AB16: =IF(U16>=2,COUNTIFS(U$2:U$93,">=2",V$2:V$93,">"&V16)+1,"n/c") -> 64
A17: Cantagalo | B17: 3301108 | C17: 19996 | D17: 1.5959604e+08 | E17: 1.576147e+08 | F17: 1.576147e+08 | G17: 46667364 | H17: 1.4818311e+08 | I17: 76742751 | J17: 4768868.8 | K17: -0.1939 | L17: 1.2 | M17: 736362.66 | N17: sim | P17: =IFERROR(G17/C17,"") -> 2333.835 | Q17: =IFERROR(G17/F17,"") -> 0.2960851 | R17: =IFERROR(D17/C17,"") -> 7981.3983 | S17: =IFERROR(E17/D17,"") -> 0.98758527 | T17: =SUM(I17:J17) -> 81511620 | U17: =COUNT(I17:J17) -> 2 | V17: =IFERROR(T17/H17,"") -> 0.55007362 | W17: =IFERROR(I17/H17,"") -> 0.51789135 | X17: =IF(M17="","",IFERROR(M17/D17,"")) -> 0.0046139156 | Y17: =IFERROR(RANK(P17,P$2:P$93),"") -> 46 | Z17: =IFERROR(RANK(Q17,Q$2:Q$93),"") -> 44 | AA17: =IFERROR(RANK(S17,S$2:S$93),"") -> 70 | AB17: =IF(U17>=2,COUNTIFS(U$2:U$93,">=2",V$2:V$93,">"&V17)+1,"n/c") -> 14 | AC17: Relatório simplificado
A18: Carapebus | B18: 3300936 | C18: 14325 | D18: 2.2969517e+08 | E18: 2.6515326e+08 | F18: 2.6515326e+08 | G18: 91552161 | H18: 2.2828626e+08 | I18: 98457959 | J18: 3294453.4 | K18: 0.3738 | L18: 1.2 | M18: 40061930 | N18: não | P18: =IFERROR(G18/C18,"") -> 6391.0758 | Q18: =IFERROR(G18/F18,"") -> 0.34528016 | R18: =IFERROR(D18/C18,"") -> 16034.567 | S18: =IFERROR(E18/D18,"") -> 1.1543702 | T18: =SUM(I18:J18) -> 1.0175241e+08 | U18: =COUNT(I18:J18) -> 2 | V18: =IFERROR(T18/H18,"") -> 0.44572289 | W18: =IFERROR(I18/H18,"") -> 0.43129165 | X18: =IF(M18="","",IFERROR(M18/D18,"")) -> 0.17441346 | Y18: =IFERROR(RANK(P18,P$2:P$93),"") -> 2 | Z18: =IFERROR(RANK(Q18,Q$2:Q$93),"") -> 11 | AA18: =IFERROR(RANK(S18,S$2:S$93),"") -> 7 | AB18: =IF(U18>=2,COUNTIFS(U$2:U$93,">=2",V$2:V$93,">"&V18)+1,"n/c") -> 58
A19: Cardoso Moreira | B19: 3301157 | C19: 13403 | D19: 1.3016787e+08 | E19: 1.1597307e+08 | F19: 1.1597307e+08 | G19: 36042007 | H19: 1.1230272e+08 | I19: 52685719 | J19: 3026794.2 | K19: 0.0036 | L19: 1.2 | M19: 7014030.9 | N19: não | P19: =IFERROR(G19/C19,"") -> 2689.1 | Q19: =IFERROR(G19/F19,"") -> 0.3107791 | R19: =IFERROR(D19/C19,"") -> 9711.846 | S19: =IFERROR(E19/D19,"") -> 0.89095005 | T19: =SUM(I19:J19) -> 55712513 | U19: =COUNT(I19:J19) -> 2 | V19: =IFERROR(T19/H19,"") -> 0.49609226 | W19: =IFERROR(I19/H19,"") -> 0.46914016 | X19: =IF(M19="","",IFERROR(M19/D19,"")) -> 0.053884502 | Y19: =IFERROR(RANK(P19,P$2:P$93),"") -> 35 | Z19: =IFERROR(RANK(Q19,Q$2:Q$93),"") -> 32 | AA19: =IFERROR(RANK(S19,S$2:S$93),"") -> 88 | AB19: =IF(U19>=2,COUNTIFS(U$2:U$93,">=2",V$2:V$93,">"&V19)+1,"n/c") -> 40
A20: Carmo | B20: 3301207 | C20: 17740 | D20: 1.5005499e+08 | E20: 1.3491256e+08 | F20: 1.3491256e+08 | G20: 44455466 | H20: 1.2620124e+08 | I20: 56927603 | J20: 2987454.5 | K20: -0.1575 | L20: 0.21340641 | M20: 4147242.7 | N20: não | P20: =IFERROR(G20/C20,"") -> 2505.9451 | Q20: =IFERROR(G20/F20,"") -> 0.32951318 | R20: =IFERROR(D20/C20,"") -> 8458.5677 | S20: =IFERROR(E20/D20,"") -> 0.89908744 | T20: =SUM(I20:J20) -> 59915057 | U20: =COUNT(I20:J20) -> 2 | V20: =IFERROR(T20/H20,"") -> 0.47475809 | W20: =IFERROR(I20/H20,"") -> 0.45108594 | X20: =IF(M20="","",IFERROR(M20/D20,"")) -> 0.027638152 | Y20: =IFERROR(RANK(P20,P$2:P$93),"") -> 42 | Z20: =IFERROR(RANK(Q20,Q$2:Q$93),"") -> 23 | AA20: =IFERROR(RANK(S20,S$2:S$93),"") -> 87 | AB20: =IF(U20>=2,COUNTIFS(U$2:U$93,">=2",V$2:V$93,">"&V20)+1,"n/c") -> 46 | AC20: Limite de dívida declarado fora do padrão (a checar)
A21: Casimiro de Abreu | B21: 3301306 | C21: 48563 | D21: 5.4824893e+08 | E21: 5.7748314e+08 | F21: 5.9802301e+08 | G21: 1.2670002e+08 | H21: 4.977814e+08 | I21: 2.1913391e+08 | J21: 7810745.7 | K21: -0.1141 | L21: 1.2 | M21: 249644.68 | N21: não | P21: =IFERROR(G21/C21,"") -> 2608.9825 | Q21: =IFERROR(G21/F21,"") -> 0.21186478 | R21: =IFERROR(D21/C21,"") -> 11289.437 | S21: =IFERROR(E21/D21,"") -> 1.0533229 | T21: =SUM(I21:J21) -> 2.2694466e+08 | U21: =COUNT(I21:J21) -> 2 | V21: =IFERROR(T21/H21,"") -> 0.45591229 | W21: =IFERROR(I21/H21,"") -> 0.44022118 | X21: =IF(M21="","",IFERROR(M21/D21,"")) -> 0.00045534914 | Y21: =IFERROR(RANK(P21,P$2:P$93),"") -> 39 | Z21: =IFERROR(RANK(Q21,Q$2:Q$93),"") -> 85 | AA21: =IFERROR(RANK(S21,S$2:S$93),"") -> 29 | AB21: =IF(U21>=2,COUNTIFS(U$2:U$93,">=2",V$2:V$93,">"&V21)+1,"n/c") -> 53
A22: Comendador Levy Gasparian | B22: 3300951 | C22: 9044 | D22: 88148636 | E22: 99753825 | F22: 99753825 | G22: 25730883 | H22: 88539849 | I22: 42223257 | J22: 2560203.7 | K22: 0.1398 | L22: 1.2 | M22: 3145553.2 | N22: não | P22: =IFERROR(G22/C22,"") -> 2845.0778 | Q22: =IFERROR(G22/F22,"") -> 0.25794383 | R22: =IFERROR(D22/C22,"") -> 9746.6427 | S22: =IFERROR(E22/D22,"") -> 1.1316548 | T22: =SUM(I22:J22) -> 44783461 | U22: =COUNT(I22:J22) -> 2 | V22: =IFERROR(T22/H22,"") -> 0.50580006 | W22: =IFERROR(I22/H22,"") -> 0.47688422 | X22: =IF(M22="","",IFERROR(M22/D22,"")) -> 0.03568465 | Y22: =IFERROR(RANK(P22,P$2:P$93),"") -> 31 | Z22: =IFERROR(RANK(Q22,Q$2:Q$93),"") -> 64 | AA22: =IFERROR(RANK(S22,S$2:S$93),"") -> 9 | AB22: =IF(U22>=2,COUNTIFS(U$2:U$93,">=2",V$2:V$93,">"&V22)+1,"n/c") -> 35
A23: Conceição de Macabu | B23: 3301405 | C23: 21769 | D23: 1.4243628e+08 | E23: 1.4337669e+08 | F23: 1.4337669e+08 | G23: 40668891 | H23: 1.340616e+08 | I23: 58868353 | J23: 3354218.5 | K23: -0.1256 | L23: 1.2 | M23: 2151949.4 | N23: não | P23: =IFERROR(G23/C23,"") -> 1868.2021 | Q23: =IFERROR(G23/F23,"") -> 0.28365065 | R23: =IFERROR(D23/C23,"") -> 6543.0786 | S23: =IFERROR(E23/D23,"") -> 1.0066023 | T23: =SUM(I23:J23) -> 62222572 | U23: =COUNT(I23:J23) -> 2 | V23: =IFERROR(T23/H23,"") -> 0.46413418 | W23: =IFERROR(I23/H23,"") -> 0.4391142 | X23: =IF(M23="","",IFERROR(M23/D23,"")) -> 0.015108155 | Y23: =IFERROR(RANK(P23,P$2:P$93),"") -> 66 | Z23: =IFERROR(RANK(Q23,Q$2:Q$93),"") -> 52 | AA23: =IFERROR(RANK(S23,S$2:S$93),"") -> 56 | AB23: =IF(U23>=2,COUNTIFS(U$2:U$93,">=2",V$2:V$93,">"&V23)+1,"n/c") -> 48 | AC23: Limite de dívida declarado já como percentual
A24: Cordeiro | B24: 3301504 | C24: 21444 | D24: 1.4864072e+08 | E24: 1.570456e+08 | F24: 1.570456e+08 | G24: 47324007 | H24: 1.3995241e+08 | I24: 61930498 | J24: 3908535.7 | K24: 0.1928 | L24: 1.2 | M24: 552443.84 | N24: não | P24: =IFERROR(G24/C24,"") -> 2206.8647 | Q24: =IFERROR(G24/F24,"") -> 0.30133927 | R24: =IFERROR(D24/C24,"") -> 6931.5763 | S24: =IFERROR(E24/D24,"") -> 1.0565449 | T24: =SUM(I24:J24) -> 65839034 | U24: =COUNT(I24:J24) -> 2 | V24: =IFERROR(T24/H24,"") -> 0.47043873 | W24: =IFERROR(I24/H24,"") -> 0.44251112 | X24: =IF(M24="","",IFERROR(M24/D24,"")) -> 0.0037166385 | Y24: =IFERROR(RANK(P24,P$2:P$93),"") -> 52 | Z24: =IFERROR(RANK(Q24,Q$2:Q$93),"") -> 40 | AA24: =IFERROR(RANK(S24,S$2:S$93),"") -> 28 | AB24: =IF(U24>=2,COUNTIFS(U$2:U$93,">=2",V$2:V$93,">"&V24)+1,"n/c") -> 47 | AC24: Limite de dívida declarado já como percentual
A25: Duas Barras | B25: 3301603 | C25: 11354 | D25: 96789026 | E25: 96859998 | F25: 96859998 | G25: 25648862 | H25: 96536660 | I25: 40330929 | J25: 2515507.7 | K25: 0.5856 | L25: 1.2 | M25: 1144981.5 | N25: não | P25: =IFERROR(G25/C25,"") -> 2259.0155 | Q25: =IFERROR(G25/F25,"") -> 0.26480345 | R25: =IFERROR(D25/C25,"") -> 8524.6632 | S25: =IFERROR(E25/D25,"") -> 1.0007333 | T25: =SUM(I25:J25) -> 42846437 | U25: =COUNT(I25:J25) -> 2 | V25: =IFERROR(T25/H25,"") -> 0.44383591 | W25: =IFERROR(I25/H25,"") -> 0.41777837 | X25: =IF(M25="","",IFERROR(M25/D25,"")) -> 0.011829662 | Y25: =IFERROR(RANK(P25,P$2:P$93),"") -> 48 | Z25: =IFERROR(RANK(Q25,Q$2:Q$93),"") -> 59 | AA25: =IFERROR(RANK(S25,S$2:S$93),"") -> 60 | AB25: =IF(U25>=2,COUNTIFS(U$2:U$93,">=2",V$2:V$93,">"&V25)+1,"n/c") -> 60 | AC25: Limite de dívida declarado já como percentual
A26: Duque de Caxias | B26: 3301702 | C26: 866347 | D26: 5.2195247e+09 | E26: 5.0491759e+09 | F26: 5.0491759e+09 | G26: 1.87648e+09 | H26: 4.8865356e+09 | I26: 1561688514 | J26: 85160950 | K26: 0.026 | L26: 1.2 | M26: 33958143 | N26: não | P26: =IFERROR(G26/C26,"") -> 2165.9682 | Q26: =IFERROR(G26/F26,"") -> 0.37164085 | R26: =IFERROR(D26/C26,"") -> 6024.7507 | S26: =IFERROR(E26/D26,"") -> 0.96736317 | T26: =SUM(I26:J26) -> 1.6468495e+09 | U26: =COUNT(I26:J26) -> 2 | V26: =IFERROR(T26/H26,"") -> 0.3370178 | W26: =IFERROR(I26/H26,"") -> 0.31959012 | X26: =IF(M26="","",IFERROR(M26/D26,"")) -> 0.0065059838 | Y26: =IFERROR(RANK(P26,P$2:P$93),"") -> 53 | Z26: =IFERROR(RANK(Q26,Q$2:Q$93),"") -> 7 | AA26: =IFERROR(RANK(S26,S$2:S$93),"") -> 74 | AB26: =IF(U26>=2,COUNTIFS(U$2:U$93,">=2",V$2:V$93,">"&V26)+1,"n/c") -> 85
A27: Engenheiro Paulo de Frontin | B27: 3301801 | C27: 12648 | D27: 1.0702959e+08 | E27: 1.2562357e+08 | F27: 1.2562357e+08 | G27: 38622637 | H27: 1.0702959e+08 | I27: 65528361 | J27: 2606640.4 | K27: -0.0893 | L27: 1.2 | M27: 7842599.3 | N27: não | P27: =IFERROR(G27/C27,"") -> 3053.6557 | Q27: =IFERROR(G27/F27,"") -> 0.30744738 | R27: =IFERROR(D27/C27,"") -> 8462.1752 | S27: =IFERROR(E27/D27,"") -> 1.1737274 | T27: =SUM(I27:J27) -> 68135001 | U27: =COUNT(I27:J27) -> 2 | V27: =IFERROR(T27/H27,"") -> 0.63659966 | W27: =IFERROR(I27/H27,"") -> 0.61224527 | X27: =IF(M27="","",IFERROR(M27/D27,"")) -> 0.073275056 | Y27: =IFERROR(RANK(P27,P$2:P$93),"") -> 27 | Z27: =IFERROR(RANK(Q27,Q$2:Q$93),"") -> 35 | AA27: =IFERROR(RANK(S27,S$2:S$93),"") -> 5 | AB27: =IF(U27>=2,COUNTIFS(U$2:U$93,">=2",V$2:V$93,">"&V27)+1,"n/c") -> 6
A28: Guapimirim | B28: 3301850 | C28: 54300 | D28: 4.6027623e+08 | E28: 5.0718403e+08 | F28: 5.0718403e+08 | G28: 1.3127099e+08 | H28: 4.5073457e+08 | I28: 1.9275324e+08 | J28: 7048784.3 | K28: -0.4127 | L28: 1.2 | M28: 7567312.9 | N28: não | P28: =IFERROR(G28/C28,"") -> 2417.5137 | Q28: =IFERROR(G28/F28,"") -> 0.2588232 | R28: =IFERROR(D28/C28,"") -> 8476.5421 | S28: =IFERROR(E28/D28,"") -> 1.1019123 | T28: =SUM(I28:J28) -> 1.9980203e+08 | U28: =COUNT(I28:J28) -> 2 | V28: =IFERROR(T28/H28,"") -> 0.44328091 | W28: =IFERROR(I28/H28,"") -> 0.42764247 | X28: =IF(M28="","",IFERROR(M28/D28,"")) -> 0.016440807 | Y28: =IFERROR(RANK(P28,P$2:P$93),"") -> 44 | Z28: =IFERROR(RANK(Q28,Q$2:Q$93),"") -> 63 | AA28: =IFERROR(RANK(S28,S$2:S$93),"") -> 14 | AB28: =IF(U28>=2,COUNTIFS(U$2:U$93,">=2",V$2:V$93,">"&V28)+1,"n/c") -> 61
A29: Iguaba Grande | B29: 3301876 | C29: 29577 | D29: 4.0608902e+08 | E29: 402040362 | F29: 402040362 | G29: 91707251 | H29: 3.9077993e+08 | I29: 1.4191008e+08 | J29: 4133787.2 | K29: -0.0895 | L29: 1.1927753 | M29: 458248.56 | N29: não | P29: =IFERROR(G29/C29,"") -> 3100.6272 | Q29: =IFERROR(G29/F29,"") -> 0.22810459 | R29: =IFERROR(D29/C29,"") -> 13729.892 | S29: =IFERROR(E29/D29,"") -> 0.99003011 | T29: =SUM(I29:J29) -> 1.4604387e+08 | U29: =COUNT(I29:J29) -> 2 | V29: =IFERROR(T29/H29,"") -> 0.37372407 | W29: =IFERROR(I29/H29,"") -> 0.36314577 | X29: =IF(M29="","",IFERROR(M29/D29,"")) -> 0.0011284436 | Y29: =IFERROR(RANK(P29,P$2:P$93),"") -> 26 | Z29: =IFERROR(RANK(Q29,Q$2:Q$93),"") -> 81 | AA29: =IFERROR(RANK(S29,S$2:S$93),"") -> 67 | AB29: =IF(U29>=2,COUNTIFS(U$2:U$93,">=2",V$2:V$93,">"&V29)+1,"n/c") -> 80
A30: Itaboraí | B30: 3301900 | C30: 240040 | D30: 1.0217684e+09 | E30: 1.1833647e+09 | F30: 1.1833647e+09 | G30: 2.7291204e+08 | H30: 9.3348743e+08 | I30: 3.9847893e+08 | J30: 14055893 | K30: -0.3984 | L30: 1.2 | M30: 21148456 | N30: não | P30: =IFERROR(G30/C30,"") -> 1136.944 | Q30: =IFERROR(G30/F30,"") -> 0.23062378 | R30: =IFERROR(D30/C30,"") -> 4256.6589 | S30: =IFERROR(E30/D30,"") -> 1.1581536 | T30: =SUM(I30:J30) -> 4.1253483e+08 | U30: =COUNT(I30:J30) -> 2 | V30: =IFERROR(T30/H30,"") -> 0.44192864 | W30: =IFERROR(I30/H30,"") -> 0.42687124 | X30: =IF(M30="","",IFERROR(M30/D30,"")) -> 0.020697895 | Y30: =IFERROR(RANK(P30,P$2:P$93),"") -> 84 | Z30: =IFERROR(RANK(Q30,Q$2:Q$93),"") -> 80 | AA30: =IFERROR(RANK(S30,S$2:S$93),"") -> 6 | AB30: =IF(U30>=2,COUNTIFS(U$2:U$93,">=2",V$2:V$93,">"&V30)+1,"n/c") -> 62
A31: Itaguaí | B31: 3302007 | C31: 123980 | D31: 1.0375647e+09 | E31: 1.0725744e+09 | F31: 1.0725744e+09 | G31: 3.0961045e+08 | H31: 9.7571944e+08 | I31: 5.871717e+08 | J31: 26170620 | K31: 0.0778 | L31: 1.2 | M31: 30812892 | N31: não | P31: =IFERROR(G31/C31,"") -> 2497.2613 | Q31: =IFERROR(G31/F31,"") -> 0.28866106 | R31: =IFERROR(D31/C31,"") -> 8368.807 | S31: =IFERROR(E31/D31,"") -> 1.0337422 | T31: =SUM(I31:J31) -> 6.1334231e+08 | U31: =COUNT(I31:J31) -> 2 | V31: =IFERROR(T31/H31,"") -> 0.6286052 | W31: =IFERROR(I31/H31,"") -> 0.60178333 | X31: =IF(M31="","",IFERROR(M31/D31,"")) -> 0.029697322 | Y31: =IFERROR(RANK(P31,P$2:P$93),"") -> 43 | Z31: =IFERROR(RANK(Q31,Q$2:Q$93),"") -> 47 | AA31: =IFERROR(RANK(S31,S$2:S$93),"") -> 40 | AB31: =IF(U31>=2,COUNTIFS(U$2:U$93,">=2",V$2:V$93,">"&V31)+1,"n/c") -> 7
A32: Italva | B32: 3302056 | C32: 14517 | D32: 1.3162413e+08 | E32: 1.4200574e+08 | F32: 1.4200574e+08 | G32: 48277339 | H32: 1.0954053e+08 | I32: 51998243 | J32: 2905469.9 | K32: -0.0836 | L32: 1.2 | M32: 2287444.7 | N32: sim | P32: =IFERROR(G32/C32,"") -> 3325.5727 | Q32: =IFERROR(G32/F32,"") -> 0.33996753 | R32: =IFERROR(D32/C32,"") -> 9066.8964 | S32: =IFERROR(E32/D32,"") -> 1.0788731 | T32: =SUM(I32:J32) -> 54903713 | U32: =COUNT(I32:J32) -> 2 | V32: =IFERROR(T32/H32,"") -> 0.50121823 | W32: =IFERROR(I32/H32,"") -> 0.47469408 | X32: =IF(M32="","",IFERROR(M32/D32,"")) -> 0.017378612 | Y32: =IFERROR(RANK(P32,P$2:P$93),"") -> 20 | Z32: =IFERROR(RANK(Q32,Q$2:Q$93),"") -> 16 | AA32: =IFERROR(RANK(S32,S$2:S$93),"") -> 21 | AB32: =IF(U32>=2,COUNTIFS(U$2:U$93,">=2",V$2:V$93,">"&V32)+1,"n/c") -> 37 | AC32: Relatório simplificado
A33: Itaocara | B33: 3302106 | C33: 23643 | D33: 1.4600151e+08 | E33: 1.5100211e+08 | F33: 1.5100211e+08 | G33: 45386384 | H33: 1.3846991e+08 | I33: 73086772 | J33: 2903429.4 | K33: -0.1531 | L33: 1.2 | M33: 620151.27 | N33: não | P33: =IFERROR(G33/C33,"") -> 1919.6542 | Q33: =IFERROR(G33/F33,"") -> 0.30056787 | R33: =IFERROR(D33/C33,"") -> 6175.253 | S33: =IFERROR(E33/D33,"") -> 1.0342504 | T33: =SUM(I33:J33) -> 75990201 | U33: =COUNT(I33:J33) -> 2 | V33: =IFERROR(T33/H33,"") -> 0.54878494 | W33: =IFERROR(I33/H33,"") -> 0.52781699 | X33: =IF(M33="","",IFERROR(M33/D33,"")) -> 0.0042475676 | Y33: =IFERROR(RANK(P33,P$2:P$93),"") -> 65 | Z33: =IFERROR(RANK(Q33,Q$2:Q$93),"") -> 42 | AA33: =IFERROR(RANK(S33,S$2:S$93),"") -> 39 | AB33: =IF(U33>=2,COUNTIFS(U$2:U$93,">=2",V$2:V$93,">"&V33)+1,"n/c") -> 17
A34: Itaperuna | B34: 3302205 | C34: 107246 | D34: 6.0117551e+08 | E34: 6.5172445e+08 | F34: 6.5172445e+08 | G34: 3.0217775e+08 | H34: 1.8929179e+08 | I34: 2.5594187e+08 | J34: 12230743 | K34: -0.3761 | L34: 1.2 | M34: 66654943 | N34: não | O34: RCL atípica | P34: =IFERROR(G34/C34,"") -> 2817.6133 | Q34: =IFERROR(G34/F34,"") -> 0.46365876 | R34: =IFERROR(D34/C34,"") -> 5605.5751 | S34: =IFERROR(E34/D34,"") -> 1.0840835 | T34: =SUM(I34:J34) -> 2.6817262e+08 | U34: =COUNT(I34:J34) -> 2 | V34: =IFERROR(T34/H34,"") -> 1.4167155 | W34: =IFERROR(I34/H34,"") -> 1.3521024 | X34: =IF(M34="","",IFERROR(M34/D34,"")) -> 0.11087435 | Y34: =IFERROR(RANK(P34,P$2:P$93),"") -> 33 | Z34: =IFERROR(RANK(Q34,Q$2:Q$93),"") -> 2 | AA34: =IFERROR(RANK(S34,S$2:S$93),"") -> 17 | AB34: =IF(U34>=2,COUNTIFS(U$2:U$93,">=2",V$2:V$93,">"&V34)+1,"n/c") -> 2 | AC34: Rcl atípica
A35: Itatiaia | B35: 3302254 | C35: 32694 | D35: 3.7554558e+08 | E35: 3.7890769e+08 | F35: 3.7890743e+08 | G35: 1.084309e+08 | H35: 3.5523789e+08 | I35: 1.8495669e+08 | J35: 10302049 | K35: 0.009 | L35: 1.2 | N35: não | P35: =IFERROR(G35/C35,"") -> 3316.5381 | Q35: =IFERROR(G35/F35,"") -> 0.28616725 | R35: =IFERROR(D35/C35,"") -> 11486.682 | S35: =IFERROR(E35/D35,"") -> 1.0089526 | T35: =SUM(I35:J35) -> 1.9525873e+08 | U35: =COUNT(I35:J35) -> 2 | V35: =IFERROR(T35/H35,"") -> 0.54965627 | W35: =IFERROR(I35/H35,"") -> 0.52065585 | X35: =IF(M35="","",IFERROR(M35/D35,"")) | Y35: =IFERROR(RANK(P35,P$2:P$93),"") -> 21 | Z35: =IFERROR(RANK(Q35,Q$2:Q$93),"") -> 50 | AA35: =IFERROR(RANK(S35,S$2:S$93),"") -> 52 | AB35: =IF(U35>=2,COUNTIFS(U$2:U$93,">=2",V$2:V$93,">"&V35)+1,"n/c") -> 16 | AC35: Sem linha de restos a pagar
A36: Japeri | B36: 3302270 | C36: 102149 | D36: 3.9029583e+08 | E36: 4.2521742e+08 | F36: 4.2566742e+08 | G36: 1.3555203e+08 | H36: 3.7503816e+08 | I36: 1.4458189e+08 | J36: 8455121.6 | K36: -0.1272 | L36: 1.2 | M36: 7597812.5 | N36: não | P36: =IFERROR(G36/C36,"") -> 1327.003 | Q36: =IFERROR(G36/F36,"") -> 0.31844586 | R36: =IFERROR(D36/C36,"") -> 3820.8482 | S36: =IFERROR(E36/D36,"") -> 1.0894747 | T36: =SUM(I36:J36) -> 1.5303701e+08 | U36: =COUNT(I36:J36) -> 2 | V36: =IFERROR(T36/H36,"") -> 0.40805718 | W36: =IFERROR(I36/H36,"") -> 0.38551249 | X36: =IF(M36="","",IFERROR(M36/D36,"")) -> 0.019466804 | Y36: =IFERROR(RANK(P36,P$2:P$93),"") -> 79 | Z36: =IFERROR(RANK(Q36,Q$2:Q$93),"") -> 27 | AA36: =IFERROR(RANK(S36,S$2:S$93),"") -> 16 | AB36: =IF(U36>=2,COUNTIFS(U$2:U$93,">=2",V$2:V$93,">"&V36)+1,"n/c") -> 73
A37: Laje do Muriaé | B37: 3302304 | C37: 7584 | D37: 89830455 | E37: 91055550 | F37: 91055550 | G37: 24905415 | H37: 70752566 | I37: 32821621 | K37: 0.2935 | L37: 1.2 | M37: 7001828 | N37: não | P37: =IFERROR(G37/C37,"") -> 3283.9419 | Q37: =IFERROR(G37/F37,"") -> 0.27351892 | R37: =IFERROR(D37/C37,"") -> 11844.733 | S37: =IFERROR(E37/D37,"") -> 1.0136379 | T37: =SUM(I37:J37) -> 32821621 | U37: =COUNT(I37:J37) -> 1 | V37: =IFERROR(T37/H37,"") -> 0.46389301 | W37: =IFERROR(I37/H37,"") -> 0.46389301 | X37: =IF(M37="","",IFERROR(M37/D37,"")) -> 0.077944925 | Y37: =IFERROR(RANK(P37,P$2:P$93),"") -> 22 | Z37: =IFERROR(RANK(Q37,Q$2:Q$93),"") -> 54 | AA37: =IFERROR(RANK(S37,S$2:S$93),"") -> 50 | AB37: =IF(U37>=2,COUNTIFS(U$2:U$93,">=2",V$2:V$93,">"&V37)+1,"n/c") -> n/c | AC37: Poderes incompletos no RGF: a soma de pessoal fica subestimada
A38: Macaé | B38: 3302403 | C38: 264138 | D38: 4.5986162e+09 | E38: 3.9282544e+09 | F38: 3.9282544e+09 | G38: 9.8924281e+08 | H38: 4.0758813e+09 | I38: 1.543364e+09 | J38: 78707852 | K38: -0.7267 | L38: 1.2 | M38: 26699222 | N38: não | P38: =IFERROR(G38/C38,"") -> 3745.1742 | Q38: =IFERROR(G38/F38,"") -> 0.25182758 | R38: =IFERROR(D38/C38,"") -> 17409.9 | S38: =IFERROR(E38/D38,"") -> 0.85422532 | T38: =SUM(I38:J38) -> 1.6220718e+09 | U38: =COUNT(I38:J38) -> 2 | V38: =IFERROR(T38/H38,"") -> 0.39796836 | W38: =IFERROR(I38/H38,"") -> 0.37865773 | X38: =IF(M38="","",IFERROR(M38/D38,"")) -> 0.0058059253 | Y38: =IFERROR(RANK(P38,P$2:P$93),"") -> 14 | Z38: =IFERROR(RANK(Q38,Q$2:Q$93),"") -> 69 | AA38: =IFERROR(RANK(S38,S$2:S$93),"") -> 91 | AB38: =IF(U38>=2,COUNTIFS(U$2:U$93,">=2",V$2:V$93,">"&V38)+1,"n/c") -> 75
A39: Macuco | B39: 3302452 | C39: 5601 | D39: 79739824 | E39: 72854928 | F39: 72854928 | G39: 24796982 | H39: 75854810 | I39: 28545657 | J39: 2135727.1 | K39: -0.4497 | L39: 1.2 | M39: 449382.83 | N39: sim | P39: =IFERROR(G39/C39,"") -> 4427.2419 | Q39: =IFERROR(G39/F39,"") -> 0.34036108 | R39: =IFERROR(D39/C39,"") -> 14236.712 | S39: =IFERROR(E39/D39,"") -> 0.913658 | T39: =SUM(I39:J39) -> 30681384 | U39: =COUNT(I39:J39) -> 2 | V39: =IFERROR(T39/H39,"") -> 0.40447513 | W39: =IFERROR(I39/H39,"") -> 0.37631967 | X39: =IF(M39="","",IFERROR(M39/D39,"")) -> 0.0056356135 | Y39: =IFERROR(RANK(P39,P$2:P$93),"") -> 8 | Z39: =IFERROR(RANK(Q39,Q$2:Q$93),"") -> 15 | AA39: =IFERROR(RANK(S39,S$2:S$93),"") -> 86 | AB39: =IF(U39>=2,COUNTIFS(U$2:U$93,">=2",V$2:V$93,">"&V39)+1,"n/c") -> 74 | AC39: Relatório simplificado
A40: Magé | B40: 3302502 | C40: 244092 | D40: 1.1958605e+09 | E40: 1.250107e+09 | F40: 1.2501046e+09 | G40: 3.7595701e+08 | H40: 1.1714336e+09 | I40: 5.9390463e+08 | J40: 11392787 | K40: 0.0479 | L40: 1.2 | M40: 37974325 | N40: não | P40: =IFERROR(G40/C40,"") -> 1540.2267 | Q40: =IFERROR(G40/F40,"") -> 0.30074043 | R40: =IFERROR(D40/C40,"") -> 4899.2202 | S40: =IFERROR(E40/D40,"") -> 1.0453619 | T40: =SUM(I40:J40) -> 6.0529742e+08 | U40: =COUNT(I40:J40) -> 2 | V40: =IFERROR(T40/H40,"") -> 0.51671507 | W40: =IFERROR(I40/H40,"") -> 0.50698956 | X40: =IF(M40="","",IFERROR(M40/D40,"")) -> 0.031754813 | Y40: =IFERROR(RANK(P40,P$2:P$93),"") -> 74 | Z40: =IFERROR(RANK(Q40,Q$2:Q$93),"") -> 41 | AA40: =IFERROR(RANK(S40,S$2:S$93),"") -> 32 | AB40: =IF(U40>=2,COUNTIFS(U$2:U$93,">=2",V$2:V$93,">"&V40)+1,"n/c") -> 28
A41: Mangaratiba | B41: 3302601 | C41: 43624 | D41: 5.6182451e+08 | E41: 6.1241948e+08 | F41: 6.1241948e+08 | G41: 1.4913346e+08 | H41: 5.4297319e+08 | I41: 2.8808251e+08 | J41: 13259361 | K41: 0.3625 | L41: 1.2 | M41: 46532113 | N41: não | P41: =IFERROR(G41/C41,"") -> 3418.6105 | Q41: =IFERROR(G41/F41,"") -> 0.24351522 | R41: =IFERROR(D41/C41,"") -> 12878.794 | S41: =IFERROR(E41/D41,"") -> 1.0900548 | T41: =SUM(I41:J41) -> 3.0134187e+08 | U41: =COUNT(I41:J41) -> 2 | V41: =IFERROR(T41/H41,"") -> 0.55498479 | W41: =IFERROR(I41/H41,"") -> 0.53056488 | X41: =IF(M41="","",IFERROR(M41/D41,"")) -> 0.082823216 | Y41: =IFERROR(RANK(P41,P$2:P$93),"") -> 18 | Z41: =IFERROR(RANK(Q41,Q$2:Q$93),"") -> 74 | AA41: =IFERROR(RANK(S41,S$2:S$93),"") -> 15 | AB41: =IF(U41>=2,COUNTIFS(U$2:U$93,">=2",V$2:V$93,">"&V41)+1,"n/c") -> 13
A42: Maricá | B42: 3302700 | C42: 211986 | D42: 6.6886245e+09 | E42: 7.1755181e+09 | F42: 7.1755181e+09 | G42: 1.0998267e+09 | H42: 6.5986499e+09 | I42: 1.2986936e+09 | J42: 36161879 | K42: -0.6945 | L42: 1.2 | M42: 19362315 | N42: não | P42: =IFERROR(G42/C42,"") -> 5188.2044 | Q42: =IFERROR(G42/F42,"") -> 0.15327489 | R42: =IFERROR(D42/C42,"") -> 31552.199 | S42: =IFERROR(E42/D42,"") -> 1.0727943 | T42: =SUM(I42:J42) -> 1.3348555e+09 | U42: =COUNT(I42:J42) -> 2 | V42: =IFERROR(T42/H42,"") -> 0.20229221 | W42: =IFERROR(I42/H42,"") -> 0.19681202 | X42: =IF(M42="","",IFERROR(M42/D42,"")) -> 0.0028948126 | Y42: =IFERROR(RANK(P42,P$2:P$93),"") -> 5 | Z42: =IFERROR(RANK(Q42,Q$2:Q$93),"") -> 92 | AA42: =IFERROR(RANK(S42,S$2:S$93),"") -> 25 | AB42: =IF(U42>=2,COUNTIFS(U$2:U$93,">=2",V$2:V$93,">"&V42)+1,"n/c") -> 89
A43: Mendes | B43: 3302809 | C43: 18049 | D43: 1.5967244e+08 | E43: 1.5726507e+08 | F43: 1.5726507e+08 | G43: 35404215 | H43: 1.4309397e+08 | I43: 62667500 | J43: 2374101.5 | K43: 0.2327 | L43: 1.2 | M43: 23154330 | N43: não | P43: =IFERROR(G43/C43,"") -> 1961.561 | Q43: =IFERROR(G43/F43,"") -> 0.22512447 | R43: =IFERROR(D43/C43,"") -> 8846.6088 | S43: =IFERROR(E43/D43,"") -> 0.98492305 | T43: =SUM(I43:J43) -> 65041601 | U43: =COUNT(I43:J43) -> 2 | V43: =IFERROR(T43/H43,"") -> 0.45453769 | W43: =IFERROR(I43/H43,"") -> 0.43794648 | X43: =IF(M43="","",IFERROR(M43/D43,"")) -> 0.14501144 | Y43: =IFERROR(RANK(P43,P$2:P$93),"") -> 61 | Z43: =IFERROR(RANK(Q43,Q$2:Q$93),"") -> 84 | AA43: =IFERROR(RANK(S43,S$2:S$93),"") -> 71 | AB43: =IF(U43>=2,COUNTIFS(U$2:U$93,">=2",V$2:V$93,">"&V43)+1,"n/c") -> 54
A44: Mesquita | B44: 3302858 | C44: 178803 | D44: 7.0131463e+08 | E44: 6.4522653e+08 | F44: 6.4522653e+08 | G44: 198701992 | H44: 6.302885e+08 | I44: 2.1898638e+08 | J44: 7074786.5 | K44: -0.0124 | L44: 1.2 | M44: 2480347.5 | N44: não | P44: =IFERROR(G44/C44,"") -> 1111.29 | Q44: =IFERROR(G44/F44,"") -> 0.30795695 | R44: =IFERROR(D44/C44,"") -> 3922.2755 | S44: =IFERROR(E44/D44,"") -> 0.92002435 | T44: =SUM(I44:J44) -> 2.2606117e+08 | U44: =COUNT(I44:J44) -> 2 | V44: =IFERROR(T44/H44,"") -> 0.35866301 | W44: =IFERROR(I44/H44,"") -> 0.34743833 | X44: =IF(M44="","",IFERROR(M44/D44,"")) -> 0.0035367115 | Y44: =IFERROR(RANK(P44,P$2:P$93),"") -> 86 | Z44: =IFERROR(RANK(Q44,Q$2:Q$93),"") -> 33 | AA44: =IFERROR(RANK(S44,S$2:S$93),"") -> 85 | AB44: =IF(U44>=2,COUNTIFS(U$2:U$93,">=2",V$2:V$93,">"&V44)+1,"n/c") -> 82
A45: Miguel Pereira | B45: 3302908 | C45: 28123 | D45: 2.8396625e+08 | E45: 2.8227523e+08 | F45: 2.8232193e+08 | G45: 85619055 | H45: 2.3492762e+08 | I45: 1.0238611e+08 | J45: 4237497.9 | K45: -0.1055 | L45: 1.2 | M45: 45673024 | N45: não | P45: =IFERROR(G45/C45,"") -> 3044.4496 | Q45: =IFERROR(G45/F45,"") -> 0.30326746 | R45: =IFERROR(D45/C45,"") -> 10097.296 | S45: =IFERROR(E45/D45,"") -> 0.994045 | T45: =SUM(I45:J45) -> 1.0662361e+08 | U45: =COUNT(I45:J45) -> 2 | V45: =IFERROR(T45/H45,"") -> 0.45385729 | W45: =IFERROR(I45/H45,"") -> 0.43581983 | X45: =IF(M45="","",IFERROR(M45/D45,"")) -> 0.16083962 | Y45: =IFERROR(RANK(P45,P$2:P$93),"") -> 29 | Z45: =IFERROR(RANK(Q45,Q$2:Q$93),"") -> 38 | AA45: =IFERROR(RANK(S45,S$2:S$93),"") -> 63 | AB45: =IF(U45>=2,COUNTIFS(U$2:U$93,">=2",V$2:V$93,">"&V45)+1,"n/c") -> 56
A46: Miracema | B46: 3303005 | C46: 28411 | D46: 1.7679982e+08 | E46: 1.9027154e+08 | F46: 1.9027154e+08 | G46: 49348302 | H46: 33240138 | I46: 40657955 | K46: 0.0872 | L46: 1.2 | M46: 8936133.8 | N46: não | O46: RCL atípica | P46: =IFERROR(G46/C46,"") -> 1736.9435 | Q46: =IFERROR(G46/F46,"") -> 0.25935724 | R46: =IFERROR(D46/C46,"") -> 6222.9354 | S46: =IFERROR(E46/D46,"") -> 1.0761976 | T46: =SUM(I46:J46) -> 40657955 | U46: =COUNT(I46:J46) -> 1 | V46: =IFERROR(T46/H46,"") -> 1.2231584 | W46: =IFERROR(I46/H46,"") -> 1.2231584 | X46: =IF(M46="","",IFERROR(M46/D46,"")) -> 0.050543796 | Y46: =IFERROR(RANK(P46,P$2:P$93),"") -> 67 | Z46: =IFERROR(RANK(Q46,Q$2:Q$93),"") -> 62 | AA46: =IFERROR(RANK(S46,S$2:S$93),"") -> 22 | AB46: =IF(U46>=2,COUNTIFS(U$2:U$93,">=2",V$2:V$93,">"&V46)+1,"n/c") -> n/c | AC46: Rcl atípica; Poderes incompletos no RGF: a soma de pessoal fica subestimada
A47: Natividade | B47: 3303104 | C47: 15550 | D47: 1.2665422e+08 | E47: 1.2930478e+08 | F47: 1.2930478e+08 | G47: 40427484 | H47: 1.1679854e+08 | I47: 50991648 | J47: 2367892.6 | K47: 0.0969 | L47: 1.2 | M47: 1140640.6 | N47: sim | P47: =IFERROR(G47/C47,"") -> 2599.8382 | Q47: =IFERROR(G47/F47,"") -> 0.31265267 | R47: =IFERROR(D47/C47,"") -> 8144.9657 | S47: =IFERROR(E47/D47,"") -> 1.0209275 | T47: =SUM(I47:J47) -> 53359541 | U47: =COUNT(I47:J47) -> 2 | V47: =IFERROR(T47/H47,"") -> 0.45685107 | W47: =IFERROR(I47/H47,"") -> 0.43657777 | X47: =IF(M47="","",IFERROR(M47/D47,"")) -> 0.0090059421 | Y47: =IFERROR(RANK(P47,P$2:P$93),"") -> 40 | Z47: =IFERROR(RANK(Q47,Q$2:Q$93),"") -> 29 | AA47: =IFERROR(RANK(S47,S$2:S$93),"") -> 47 | AB47: =IF(U47>=2,COUNTIFS(U$2:U$93,">=2",V$2:V$93,">"&V47)+1,"n/c") -> 52 | AC47: Relatório simplificado
A48: Nilópolis | B48: 3303203 | C48: 155544 | D48: 5.5873186e+08 | E48: 6.1668703e+08 | F48: 6.1668703e+08 | G48: 2.0591306e+08 | H48: 5.0846521e+08 | I48: 1.8575079e+08 | J48: 11531601 | K48: 0.0529 | L48: 1.2 | M48: 425665.76 | N48: não | P48: =IFERROR(G48/C48,"") -> 1323.8251 | Q48: =IFERROR(G48/F48,"") -> 0.33390204 | R48: =IFERROR(D48/C48,"") -> 3592.1145 | S48: =IFERROR(E48/D48,"") -> 1.1037263 | T48: =SUM(I48:J48) -> 1.9728239e+08 | U48: =COUNT(I48:J48) -> 2 | V48: =IFERROR(T48/H48,"") -> 0.38799586 | W48: =IFERROR(I48/H48,"") -> 0.36531662 | X48: =IF(M48="","",IFERROR(M48/D48,"")) -> 0.00076184265 | Y48: =IFERROR(RANK(P48,P$2:P$93),"") -> 80 | Z48: =IFERROR(RANK(Q48,Q$2:Q$93),"") -> 21 | AA48: =IFERROR(RANK(S48,S$2:S$93),"") -> 13 | AB48: =IF(U48>=2,COUNTIFS(U$2:U$93,">=2",V$2:V$93,">"&V48)+1,"n/c") -> 77
A49: Niterói | B49: 3303302 | C49: 516720 | D49: 6.1060294e+09 | E49: 5.6327431e+09 | F49: 5.6327431e+09 | G49: 8.7747891e+08 | H49: 5.8884339e+09 | I49: 2.1632703e+09 | J49: 1.2310752e+08 | K49: -0.7254 | L49: 1.2 | M49: 1.8192203e+08 | N49: não | P49: =IFERROR(G49/C49,"") -> 1698.171 | Q49: =IFERROR(G49/F49,"") -> 0.15578181 | R49: =IFERROR(D49/C49,"") -> 11816.902 | S49: =IFERROR(E49/D49,"") -> 0.92248869 | T49: =SUM(I49:J49) -> 2.2863778e+09 | U49: =COUNT(I49:J49) -> 2 | V49: =IFERROR(T49/H49,"") -> 0.38828283 | W49: =IFERROR(I49/H49,"") -> 0.36737617 | X49: =IF(M49="","",IFERROR(M49/D49,"")) -> 0.029793835 | Y49: =IFERROR(RANK(P49,P$2:P$93),"") -> 69 | Z49: =IFERROR(RANK(Q49,Q$2:Q$93),"") -> 91 | AA49: =IFERROR(RANK(S49,S$2:S$93),"") -> 84 | AB49: =IF(U49>=2,COUNTIFS(U$2:U$93,">=2",V$2:V$93,">"&V49)+1,"n/c") -> 76
A50: Nova Friburgo | B50: 3303401 | C50: 203328 | D50: 8.2810819e+08 | E50: 8.552048e+08 | F50: 8.552048e+08 | G50: 3.1005002e+08 | H50: 7.9943634e+08 | I50: 4.1743148e+08 | J50: 13524926 | K50: -0.1991 | L50: 1.2 | M50: 9711775.9 | N50: não | P50: =IFERROR(G50/C50,"") -> 1524.8762 | Q50: =IFERROR(G50/F50,"") -> 0.36254476 | R50: =IFERROR(D50/C50,"") -> 4072.7701 | S50: =IFERROR(E50/D50,"") -> 1.0327211 | T50: =SUM(I50:J50) -> 4.3095641e+08 | U50: =COUNT(I50:J50) -> 2 | V50: =IFERROR(T50/H50,"") -> 0.53907533 | W50: =IFERROR(I50/H50,"") -> 0.52215725 | X50: =IF(M50="","",IFERROR(M50/D50,"")) -> 0.011727666 | Y50: =IFERROR(RANK(P50,P$2:P$93),"") -> 75 | Z50: =IFERROR(RANK(Q50,Q$2:Q$93),"") -> 9 | AA50: =IFERROR(RANK(S50,S$2:S$93),"") -> 41 | AB50: =IF(U50>=2,COUNTIFS(U$2:U$93,">=2",V$2:V$93,">"&V50)+1,"n/c") -> 19
A51: Nova Iguaçu | B51: 3303500 | C51: 843046 | D51: 2.6381862e+09 | E51: 2.7725147e+09 | F51: 2.7725147e+09 | G51: 8.6476962e+08 | H51: 2.380991e+09 | I51: 1.0168616e+09 | J51: 19331781 | K51: 0.4458 | L51: 1.2 | M51: 18094228 | N51: não | P51: =IFERROR(G51/C51,"") -> 1025.768 | Q51: =IFERROR(G51/F51,"") -> 0.31190804 | R51: =IFERROR(D51/C51,"") -> 3129.3502 | S51: =IFERROR(E51/D51,"") -> 1.050917 | T51: =SUM(I51:J51) -> 1.0361934e+09 | U51: =COUNT(I51:J51) -> 2 | V51: =IFERROR(T51/H51,"") -> 0.43519416 | W51: =IFERROR(I51/H51,"") -> 0.42707495 | X51: =IF(M51="","",IFERROR(M51/D51,"")) -> 0.0068585867 | Y51: =IFERROR(RANK(P51,P$2:P$93),"") -> 89 | Z51: =IFERROR(RANK(Q51,Q$2:Q$93),"") -> 31 | AA51: =IFERROR(RANK(S51,S$2:S$93),"") -> 31 | AB51: =IF(U51>=2,COUNTIFS(U$2:U$93,">=2",V$2:V$93,">"&V51)+1,"n/c") -> 65 | AC51: Limite de dívida declarado já como percentual
A52: Paracambi | B52: 3303609 | C52: 43656 | D52: 2.7917325e+08 | E52: 2.7887244e+08 | F52: 2.7887244e+08 | G52: 94528222 | H52: 2.6213793e+08 | I52: 84375894 | J52: 3724078 | K52: -0.0034 | L52: 1.2670739 | M52: 1120011.9 | N52: não | P52: =IFERROR(G52/C52,"") -> 2165.2974 | Q52: =IFERROR(G52/F52,"") -> 0.33896581 | R52: =IFERROR(D52/C52,"") -> 6394.8426 | S52: =IFERROR(E52/D52,"") -> 0.99892251 | T52: =SUM(I52:J52) -> 88099972 | U52: =COUNT(I52:J52) -> 2 | V52: =IFERROR(T52/H52,"") -> 0.3360825 | W52: =IFERROR(I52/H52,"") -> 0.32187594 | X52: =IF(M52="","",IFERROR(M52/D52,"")) -> 0.0040118883 | Y52: =IFERROR(RANK(P52,P$2:P$93),"") -> 54 | Z52: =IFERROR(RANK(Q52,Q$2:Q$93),"") -> 18 | AA52: =IFERROR(RANK(S52,S$2:S$93),"") -> 61 | AB52: =IF(U52>=2,COUNTIFS(U$2:U$93,">=2",V$2:V$93,">"&V52)+1,"n/c") -> 87 | AC52: Limite de dívida declarado fora do padrão (a checar)
A53: Paraty | B53: 3303807 | C53: 47614 | D53: 5.2757632e+08 | E53: 5.8269177e+08 | F53: 5.8269177e+08 | G53: 1.525482e+08 | H53: 5.2179576e+08 | I53: 1.9342291e+08 | J53: 8257531.4 | K53: -0.2132 | L53: 1.2 | M53: 11197127 | N53: não | P53: =IFERROR(G53/C53,"") -> 3203.8517 | Q53: =IFERROR(G53/F53,"") -> 0.26179912 | R53: =IFERROR(D53/C53,"") -> 11080.277 | S53: =IFERROR(E53/D53,"") -> 1.1044692 | T53: =SUM(I53:J53) -> 2.0168044e+08 | U53: =COUNT(I53:J53) -> 2 | V53: =IFERROR(T53/H53,"") -> 0.38651223 | W53: =IFERROR(I53/H53,"") -> 0.37068701 | X53: =IF(M53="","",IFERROR(M53/D53,"")) -> 0.02122371 | Y53: =IFERROR(RANK(P53,P$2:P$93),"") -> 25 | Z53: =IFERROR(RANK(Q53,Q$2:Q$93),"") -> 61 | AA53: =IFERROR(RANK(S53,S$2:S$93),"") -> 12 | AB53: =IF(U53>=2,COUNTIFS(U$2:U$93,">=2",V$2:V$93,">"&V53)+1,"n/c") -> 78
A54: Paraíba do Sul | B54: 3303708 | C54: 44467 | D54: 2.6809656e+08 | E54: 2.8984211e+08 | F54: 2.8984211e+08 | G54: 69315509 | H54: 2.2899757e+08 | I54: 1.1220089e+08 | J54: 4687833.5 | K54: 0.4209 | L54: 1.2 | M54: 19137154 | N54: não | P54: =IFERROR(G54/C54,"") -> 1558.8078 | Q54: =IFERROR(G54/F54,"") -> 0.2391492 | R54: =IFERROR(D54/C54,"") -> 6029.1129 | S54: =IFERROR(E54/D54,"") -> 1.0811109 | T54: =SUM(I54:J54) -> 1.1688873e+08 | U54: =COUNT(I54:J54) -> 2 | V54: =IFERROR(T54/H54,"") -> 0.51043654 | W54: =IFERROR(I54/H54,"") -> 0.48996543 | X54: =IF(M54="","",IFERROR(M54/D54,"")) -> 0.071381573 | Y54: =IFERROR(RANK(P54,P$2:P$93),"") -> 73 | Z54: =IFERROR(RANK(Q54,Q$2:Q$93),"") -> 76 | AA54: =IFERROR(RANK(S54,S$2:S$93),"") -> 19 | AB54: =IF(U54>=2,COUNTIFS(U$2:U$93,">=2",V$2:V$93,">"&V54)+1,"n/c") -> 34
A55: Paty do Alferes | B55: 3303856 | C55: 31345 | D55: 2.0849752e+08 | E55: 2.2430906e+08 | F55: 2.2430906e+08 | G55: 53590491 | H55: 1.8538972e+08 | I55: 96006782 | J55: 4363758.7 | K55: -0.1382 | L55: 1.2 | M55: 12801519 | N55: não | P55: =IFERROR(G55/C55,"") -> 1709.6982 | Q55: =IFERROR(G55/F55,"") -> 0.23891362 | R55: =IFERROR(D55/C55,"") -> 6651.6996 | S55: =IFERROR(E55/D55,"") -> 1.0758356 | T55: =SUM(I55:J55) -> 1.0037054e+08 | U55: =COUNT(I55:J55) -> 2 | V55: =IFERROR(T55/H55,"") -> 0.54140294 | W55: =IFERROR(I55/H55,"") -> 0.51786464 | X55: =IF(M55="","",IFERROR(M55/D55,"")) -> 0.061398903 | Y55: =IFERROR(RANK(P55,P$2:P$93),"") -> 68 | Z55: =IFERROR(RANK(Q55,Q$2:Q$93),"") -> 77 | AA55: =IFERROR(RANK(S55,S$2:S$93),"") -> 23 | AB55: =IF(U55>=2,COUNTIFS(U$2:U$93,">=2",V$2:V$93,">"&V55)+1,"n/c") -> 18
A56: Petrópolis | B56: 3303906 | C56: 294983 | D56: 1.7732081e+09 | E56: 1.8121138e+09 | F56: 1.8121138e+09 | G56: 5.7829318e+08 | H56: 1.6685187e+09 | I56: 6.7606113e+08 | J56: 25995453 | K56: 0.2552 | L56: 1.2 | M56: 81120263 | N56: não | P56: =IFERROR(G56/C56,"") -> 1960.4288 | Q56: =IFERROR(G56/F56,"") -> 0.3191263 | R56: =IFERROR(D56/C56,"") -> 6011.2215 | S56: =IFERROR(E56/D56,"") -> 1.0219409 | T56: =SUM(I56:J56) -> 7.0205658e+08 | U56: =COUNT(I56:J56) -> 2 | V56: =IFERROR(T56/H56,"") -> 0.42076637 | W56: =IFERROR(I56/H56,"") -> 0.40518642 | X56: =IF(M56="","",IFERROR(M56/D56,"")) -> 0.045747739 | Y56: =IFERROR(RANK(P56,P$2:P$93),"") -> 62 | Z56: =IFERROR(RANK(Q56,Q$2:Q$93),"") -> 26 | AA56: =IFERROR(RANK(S56,S$2:S$93),"") -> 46 | AB56: =IF(U56>=2,COUNTIFS(U$2:U$93,">=2",V$2:V$93,">"&V56)+1,"n/c") -> 69
A57: Pinheiral | B57: 3303955 | C57: 25085 | D57: 1.653806e+08 | E57: 1.6916684e+08 | F57: 1.6916684e+08 | G57: 57822498 | H57: 1.599454e+08 | I57: 74562231 | J57: 4021159.5 | K57: -0.0587 | L57: 1.2 | M57: 761333.1 | N57: sim | P57: =IFERROR(G57/C57,"") -> 2305.0627 | Q57: =IFERROR(G57/F57,"") -> 0.34180752 | R57: =IFERROR(D57/C57,"") -> 6592.8086 | S57: =IFERROR(E57/D57,"") -> 1.0228941 | T57: =SUM(I57:J57) -> 78583390 | U57: =COUNT(I57:J57) -> 2 | V57: =IFERROR(T57/H57,"") -> 0.49131384 | W57: =IFERROR(I57/H57,"") -> 0.46617301 | X57: =IF(M57="","",IFERROR(M57/D57,"")) -> 0.0046035211 | Y57: =IFERROR(RANK(P57,P$2:P$93),"") -> 47 | Z57: =IFERROR(RANK(Q57,Q$2:Q$93),"") -> 13 | AA57: =IFERROR(RANK(S57,S$2:S$93),"") -> 44 | AB57: =IF(U57>=2,COUNTIFS(U$2:U$93,">=2",V$2:V$93,">"&V57)+1,"n/c") -> 41 | AC57: Relatório simplificado
A58: Piraí | B58: 3304003 | C58: 29054 | D58: 3.235466e+08 | E58: 3.2108157e+08 | F58: 3.2108157e+08 | G58: 1.0979877e+08 | H58: 2.8406655e+08 | I58: 1.2466105e+08 | J58: 6160281.5 | K58: -0.1481 | L58: 1.2005275 | M58: 2117467 | N58: sim | P58: =IFERROR(G58/C58,"") -> 3779.1274 | Q58: =IFERROR(G58/F58,"") -> 0.34196534 | R58: =IFERROR(D58/C58,"") -> 11136.043 | S58: =IFERROR(E58/D58,"") -> 0.99238122 | T58: =SUM(I58:J58) -> 1.3082133e+08 | U58: =COUNT(I58:J58) -> 2 | V58: =IFERROR(T58/H58,"") -> 0.46053058 | W58: =IFERROR(I58/H58,"") -> 0.43884453 | X58: =IF(M58="","",IFERROR(M58/D58,"")) -> 0.0065445502 | Y58: =IFERROR(RANK(P58,P$2:P$93),"") -> 13 | Z58: =IFERROR(RANK(Q58,Q$2:Q$93),"") -> 12 | AA58: =IFERROR(RANK(S58,S$2:S$93),"") -> 64 | AB58: =IF(U58>=2,COUNTIFS(U$2:U$93,">=2",V$2:V$93,">"&V58)+1,"n/c") -> 49 | AC58: Relatório simplificado
A59: Porciúncula | B59: 3304102 | C59: 17832 | D59: 1.523117e+08 | E59: 2.0164898e+08 | F59: 2.0164898e+08 | G59: 47216339 | H59: 1.3224631e+08 | I59: 70698366 | J59: 3294079.3 | K59: -0.1266 | L59: 1.2 | M59: 2627584.6 | N59: não | P59: =IFERROR(G59/C59,"") -> 2647.8431 | Q59: =IFERROR(G59/F59,"") -> 0.23415114 | R59: =IFERROR(D59/C59,"") -> 8541.4818 | S59: =IFERROR(E59/D59,"") -> 1.3239231 | T59: =SUM(I59:J59) -> 73992445 | U59: =COUNT(I59:J59) -> 2 | V59: =IFERROR(T59/H59,"") -> 0.55950482 | W59: =IFERROR(I59/H59,"") -> 0.53459615 | X59: =IF(M59="","",IFERROR(M59/D59,"")) -> 0.017251363 | Y59: =IFERROR(RANK(P59,P$2:P$93),"") -> 38 | Z59: =IFERROR(RANK(Q59,Q$2:Q$93),"") -> 78 | AA59: =IFERROR(RANK(S59,S$2:S$93),"") -> 1 | AB59: =IF(U59>=2,COUNTIFS(U$2:U$93,">=2",V$2:V$93,">"&V59)+1,"n/c") -> 10
A60: Porto Real | B60: 3304110 | C60: 21064 | D60: 2.9920552e+08 | E60: 2.8465484e+08 | F60: 2.8465484e+08 | G60: 94323288 | H60: 2.9325754e+08 | I60: 1.1302136e+08 | J60: 7182085.5 | K60: 0.0824 | L60: 1.2 | M60: 15258122 | N60: sim | P60: =IFERROR(G60/C60,"") -> 4477.9381 | Q60: =IFERROR(G60/F60,"") -> 0.33136022 | R60: =IFERROR(D60/C60,"") -> 14204.592 | S60: =IFERROR(E60/D60,"") -> 0.95136893 | T60: =SUM(I60:J60) -> 1.2020345e+08 | U60: =COUNT(I60:J60) -> 2 | V60: =IFERROR(T60/H60,"") -> 0.4098904 | W60: =IFERROR(I60/H60,"") -> 0.38539968 | X60: =IF(M60="","",IFERROR(M60/D60,"")) -> 0.050995454 | Y60: =IFERROR(RANK(P60,P$2:P$93),"") -> 7 | Z60: =IFERROR(RANK(Q60,Q$2:Q$93),"") -> 22 | AA60: =IFERROR(RANK(S60,S$2:S$93),"") -> 79 | AB60: =IF(U60>=2,COUNTIFS(U$2:U$93,">=2",V$2:V$93,">"&V60)+1,"n/c") -> 72 | AC60: Relatório simplificado
A61: Quatis | B61: 3304128 | C61: 14158 | D61: 1.3918449e+08 | E61: 1.4544207e+08 | F61: 1.4544207e+08 | G61: 29866096 | H61: 118719497 | I61: 55596696 | J61: 2723229.7 | K61: -2.3124 | L61: 1.2 | M61: 1891908.6 | N61: sim | P61: =IFERROR(G61/C61,"") -> 2109.4855 | Q61: =IFERROR(G61/F61,"") -> 0.20534701 | R61: =IFERROR(D61/C61,"") -> 9830.8015 | S61: =IFERROR(E61/D61,"") -> 1.0449589 | T61: =SUM(I61:J61) -> 58319926 | U61: =COUNT(I61:J61) -> 2 | V61: =IFERROR(T61/H61,"") -> 0.49124135 | W61: =IFERROR(I61/H61,"") -> 0.468303 | X61: =IF(M61="","",IFERROR(M61/D61,"")) -> 0.013592812 | Y61: =IFERROR(RANK(P61,P$2:P$93),"") -> 55 | Z61: =IFERROR(RANK(Q61,Q$2:Q$93),"") -> 86 | AA61: =IFERROR(RANK(S61,S$2:S$93),"") -> 34 | AB61: =IF(U61>=2,COUNTIFS(U$2:U$93,">=2",V$2:V$93,">"&V61)+1,"n/c") -> 42 | AC61: Relatório simplificado
A62: Queimados | B62: 3304144 | C62: 149093 | D62: 5.3353959e+08 | E62: 5.2693476e+08 | F62: 5.2693476e+08 | G62: 1.4959482e+08 | H62: 4.9139879e+08 | I62: 2.2066307e+08 | J62: 5402604.3 | K62: -0.303 | L62: 1.2 | M62: 9253646.9 | N62: não | P62: =IFERROR(G62/C62,"") -> 1003.3658 | Q62: =IFERROR(G62/F62,"") -> 0.28389628 | R62: =IFERROR(D62/C62,"") -> 3578.569 | S62: =IFERROR(E62/D62,"") -> 0.98762072 | T62: =SUM(I62:J62) -> 2.2606567e+08 | U62: =COUNT(I62:J62) -> 2 | V62: =IFERROR(T62/H62,"") -> 0.46004524 | W62: =IFERROR(I62/H62,"") -> 0.4490509 | X62: =IF(M62="","",IFERROR(M62/D62,"")) -> 0.01734388 | Y62: =IFERROR(RANK(P62,P$2:P$93),"") -> 90 | Z62: =IFERROR(RANK(Q62,Q$2:Q$93),"") -> 51 | AA62: =IFERROR(RANK(S62,S$2:S$93),"") -> 69 | AB62: =IF(U62>=2,COUNTIFS(U$2:U$93,">=2",V$2:V$93,">"&V62)+1,"n/c") -> 50
A63: Quissamã | B63: 3304151 | C63: 23126 | D63: 4.8210307e+08 | E63: 4.7691567e+08 | F63: 4.7691567e+08 | G63: 1.2768779e+08 | H63: 4.663805e+08 | I63: 1.9044416e+08 | J63: 9201296 | K63: -0.0095 | L63: 1.1995233 | M63: 18112120 | N63: sim | P63: =IFERROR(G63/C63,"") -> 5521.3953 | Q63: =IFERROR(G63/F63,"") -> 0.26773662 | R63: =IFERROR(D63/C63,"") -> 20846.799 | S63: =IFERROR(E63/D63,"") -> 0.98924006 | T63: =SUM(I63:J63) -> 1.9964546e+08 | U63: =COUNT(I63:J63) -> 2 | V63: =IFERROR(T63/H63,"") -> 0.4280742 | W63: =IFERROR(I63/H63,"") -> 0.40834504 | X63: =IF(M63="","",IFERROR(M63/D63,"")) -> 0.037568979 | Y63: =IFERROR(RANK(P63,P$2:P$93),"") -> 4 | Z63: =IFERROR(RANK(Q63,Q$2:Q$93),"") -> 58 | AA63: =IFERROR(RANK(S63,S$2:S$93),"") -> 68 | AB63: =IF(U63>=2,COUNTIFS(U$2:U$93,">=2",V$2:V$93,">"&V63)+1,"n/c") -> 67 | AC63: Relatório simplificado
A64: Resende | B64: 3304201 | C64: 137612 | D64: 1.0180572e+09 | E64: 9.7017982e+08 | F64: 9.7017982e+08 | G64: 3.6723016e+08 | H64: 9.278879e+08 | I64: 4.6993898e+08 | J64: 18693358 | K64: -0.2678 | L64: 1.2 | M64: 4261121.9 | N64: não | P64: =IFERROR(G64/C64,"") -> 2668.5911 | Q64: =IFERROR(G64/F64,"") -> 0.37851763 | R64: =IFERROR(D64/C64,"") -> 7398.0266 | S64: =IFERROR(E64/D64,"") -> 0.95297179 | T64: =SUM(I64:J64) -> 4.8863234e+08 | U64: =COUNT(I64:J64) -> 2 | V64: =IFERROR(T64/H64,"") -> 0.52660708 | W64: =IFERROR(I64/H64,"") -> 0.50646094 | X64: =IF(M64="","",IFERROR(M64/D64,"")) -> 0.0041855426 | Y64: =IFERROR(RANK(P64,P$2:P$93),"") -> 36 | Z64: =IFERROR(RANK(Q64,Q$2:Q$93),"") -> 5 | AA64: =IFERROR(RANK(S64,S$2:S$93),"") -> 78 | AB64: =IF(U64>=2,COUNTIFS(U$2:U$93,">=2",V$2:V$93,">"&V64)+1,"n/c") -> 23
A65: Rio Bonito | B65: 3304300 | C65: 59113 | D65: 4.2459113e+08 | E65: 5.187402e+08 | F65: 5.187402e+08 | G65: 1.894191e+08 | H65: 4.0377578e+08 | I65: 2.0286455e+08 | J65: 7401052.2 | K65: 0.1296 | L65: 1.2 | M65: 1.2143154e+08 | N65: não | P65: =IFERROR(G65/C65,"") -> 3204.356 | Q65: =IFERROR(G65/F65,"") -> 0.36515215 | R65: =IFERROR(D65/C65,"") -> 7182.7032 | S65: =IFERROR(E65/D65,"") -> 1.2217405 | T65: =SUM(I65:J65) -> 2.102656e+08 | U65: =COUNT(I65:J65) -> 2 | V65: =IFERROR(T65/H65,"") -> 0.52074843 | W65: =IFERROR(I65/H65,"") -> 0.50241882 | X65: =IF(M65="","",IFERROR(M65/D65,"")) -> 0.2859964 | Y65: =IFERROR(RANK(P65,P$2:P$93),"") -> 24 | Z65: =IFERROR(RANK(Q65,Q$2:Q$93),"") -> 8 | AA65: =IFERROR(RANK(S65,S$2:S$93),"") -> 2 | AB65: =IF(U65>=2,COUNTIFS(U$2:U$93,">=2",V$2:V$93,">"&V65)+1,"n/c") -> 26
A66: Rio Claro | B66: 3304409 | C66: 17950 | D66: 1.9423651e+08 | E66: 1.9719291e+08 | F66: 1.9719291e+08 | G66: 59980815 | H66: 1.8658621e+08 | I66: 91907887 | J66: 4021729.5 | K66: 0.0353 | L66: 1.2 | M66: 3066303.4 | N66: não | P66: =IFERROR(G66/C66,"") -> 3341.5496 | Q66: =IFERROR(G66/F66,"") -> 0.30417329 | R66: =IFERROR(D66/C66,"") -> 10820.975 | S66: =IFERROR(E66/D66,"") -> 1.0152206 | T66: =SUM(I66:J66) -> 95929616 | U66: =COUNT(I66:J66) -> 2 | V66: =IFERROR(T66/H66,"") -> 0.51413025 | W66: =IFERROR(I66/H66,"") -> 0.49257598 | X66: =IF(M66="","",IFERROR(M66/D66,"")) -> 0.015786442 | Y66: =IFERROR(RANK(P66,P$2:P$93),"") -> 19 | Z66: =IFERROR(RANK(Q66,Q$2:Q$93),"") -> 37 | AA66: =IFERROR(RANK(S66,S$2:S$93),"") -> 49 | AB66: =IF(U66>=2,COUNTIFS(U$2:U$93,">=2",V$2:V$93,">"&V66)+1,"n/c") -> 29
A67: Rio das Flores | B67: 3304508 | C67: 9264 | D67: 1.0358202e+08 | E67: 1.1650905e+08 | F67: 1.1650905e+08 | G67: 34434303 | H67: 1.0063123e+08 | I67: 40738600 | J67: 2519325.1 | K67: 0.6119 | L67: 1.2 | M67: 14457417 | N67: sim | P67: =IFERROR(G67/C67,"") -> 3717.0016 | Q67: =IFERROR(G67/F67,"") -> 0.29555046 | R67: =IFERROR(D67/C67,"") -> 11181.134 | S67: =IFERROR(E67/D67,"") -> 1.1247999 | T67: =SUM(I67:J67) -> 43257925 | U67: =COUNT(I67:J67) -> 2 | V67: =IFERROR(T67/H67,"") -> 0.42986581 | W67: =IFERROR(I67/H67,"") -> 0.40483059 | X67: =IF(M67="","",IFERROR(M67/D67,"")) -> 0.13957457 | Y67: =IFERROR(RANK(P67,P$2:P$93),"") -> 15 | Z67: =IFERROR(RANK(Q67,Q$2:Q$93),"") -> 45 | AA67: =IFERROR(RANK(S67,S$2:S$93),"") -> 10 | AB67: =IF(U67>=2,COUNTIFS(U$2:U$93,">=2",V$2:V$93,">"&V67)+1,"n/c") -> 66 | AC67: Relatório simplificado
A68: Rio das Ostras | B68: 3304524 | C68: 168099 | D68: 1.0980405e+09 | E68: 1.0936083e+09 | F68: 1.0936083e+09 | G68: 2.7156876e+08 | H68: 1.0374608e+09 | I68: 5.6246041e+08 | J68: 23399149 | K68: -0.0529 | L68: 1.2 | M68: 17299429 | N68: não | P68: =IFERROR(G68/C68,"") -> 1615.5287 | Q68: =IFERROR(G68/F68,"") -> 0.24832361 | R68: =IFERROR(D68/C68,"") -> 6532.1061 | S68: =IFERROR(E68/D68,"") -> 0.99596354 | T68: =SUM(I68:J68) -> 5.8585955e+08 | U68: =COUNT(I68:J68) -> 2 | V68: =IFERROR(T68/H68,"") -> 0.56470526 | W68: =IFERROR(I68/H68,"") -> 0.54215101 | X68: =IF(M68="","",IFERROR(M68/D68,"")) -> 0.015754819 | Y68: =IFERROR(RANK(P68,P$2:P$93),"") -> 72 | Z68: =IFERROR(RANK(Q68,Q$2:Q$93),"") -> 72 | AA68: =IFERROR(RANK(S68,S$2:S$93),"") -> 62 | AB68: =IF(U68>=2,COUNTIFS(U$2:U$93,">=2",V$2:V$93,">"&V68)+1,"n/c") -> 9
A69: Rio de Janeiro (capital) | B69: 3304557 | C69: 6729894 | D69: 3.8957558e+10 | E69: 3.9263761e+10 | F69: 3.963408e+10 | G69: 7.6426443e+09 | H69: 3.444065e+10 | I69: 1.6010609e+10 | J69: 8.0095981e+08 | K69: 0.487 | L69: 1.2 | M69: 42571319 | N69: não | P69: =IFERROR(G69/C69,"") -> 1135.6263 | Q69: =IFERROR(G69/F69,"") -> 0.19283012 | R69: =IFERROR(D69/C69,"") -> 5788.7327 | S69: =IFERROR(E69/D69,"") -> 1.0078599 | T69: =SUM(I69:J69) -> 1.6811569e+10 | U69: =COUNT(I69:J69) -> 2 | V69: =IFERROR(T69/H69,"") -> 0.48813157 | W69: =IFERROR(I69/H69,"") -> 0.46487533 | X69: =IF(M69="","",IFERROR(M69/D69,"")) -> 0.0010927615 | Y69: =IFERROR(RANK(P69,P$2:P$93),"") -> 85 | Z69: =IFERROR(RANK(Q69,Q$2:Q$93),"") -> 88 | AA69: =IFERROR(RANK(S69,S$2:S$93),"") -> 54 | AB69: =IF(U69>=2,COUNTIFS(U$2:U$93,">=2",V$2:V$93,">"&V69)+1,"n/c") -> 45
A70: Santa Maria Madalena | B70: 3304607 | C70: 10579 | D70: 1.0160952e+08 | E70: 98032640 | F70: 98032640 | G70: 26598764 | H70: 1.004215e+08 | I70: 40758766 | J70: 3418074 | K70: -0.0867 | L70: 1.2 | M70: 5294814.4 | N70: não | P70: =IFERROR(G70/C70,"") -> 2514.2985 | Q70: =IFERROR(G70/F70,"") -> 0.27132559 | R70: =IFERROR(D70/C70,"") -> 9604.8326 | S70: =IFERROR(E70/D70,"") -> 0.96479774 | T70: =SUM(I70:J70) -> 44176840 | U70: =COUNT(I70:J70) -> 2 | V70: =IFERROR(T70/H70,"") -> 0.43991416 | W70: =IFERROR(I70/H70,"") -> 0.40587689 | X70: =IF(M70="","",IFERROR(M70/D70,"")) -> 0.05210943 | Y70: =IFERROR(RANK(P70,P$2:P$93),"") -> 41 | Z70: =IFERROR(RANK(Q70,Q$2:Q$93),"") -> 56 | AA70: =IFERROR(RANK(S70,S$2:S$93),"") -> 75 | AB70: =IF(U70>=2,COUNTIFS(U$2:U$93,">=2",V$2:V$93,">"&V70)+1,"n/c") -> 63
A71: Santo Antônio de Pádua | B71: 3304706 | C71: 43686 | D71: 2.5375429e+08 | E71: 2.8215487e+08 | F71: 2.8215487e+08 | G71: 98442916 | H71: 2.3868573e+08 | I71: 86124970 | J71: 5708307.9 | K71: -0.0179 | L71: 1.2 | M71: 73795.62 | N71: não | P71: =IFERROR(G71/C71,"") -> 2253.4202 | Q71: =IFERROR(G71/F71,"") -> 0.34889675 | R71: =IFERROR(D71/C71,"") -> 5808.5952 | S71: =IFERROR(E71/D71,"") -> 1.1119216 | T71: =SUM(I71:J71) -> 91833278 | U71: =COUNT(I71:J71) -> 2 | V71: =IFERROR(T71/H71,"") -> 0.38474558 | W71: =IFERROR(I71/H71,"") -> 0.36083 | X71: =IF(M71="","",IFERROR(M71/D71,"")) -> 0.00029081526 | Y71: =IFERROR(RANK(P71,P$2:P$93),"") -> 49 | Z71: =IFERROR(RANK(Q71,Q$2:Q$93),"") -> 10 | AA71: =IFERROR(RANK(S71,S$2:S$93),"") -> 11 | AB71: =IF(U71>=2,COUNTIFS(U$2:U$93,">=2",V$2:V$93,">"&V71)+1,"n/c") -> 79
A72: Sapucaia | B72: 3305406 | C72: 18289 | D72: 1.7223829e+08 | E72: 1.7052684e+08 | F72: 1.7052684e+08 | G72: 40928347 | H72: 1.6099035e+08 | I72: 50142356 | J72: 4034595.4 | K72: -0.3121 | L72: 1.2 | M72: 1110000.8 | N72: não | P72: =IFERROR(G72/C72,"") -> 2237.8668 | Q72: =IFERROR(G72/F72,"") -> 0.24001117 | R72: =IFERROR(D72/C72,"") -> 9417.5893 | S72: =IFERROR(E72/D72,"") -> 0.99006347 | T72: =SUM(I72:J72) -> 54176951 | U72: =COUNT(I72:J72) -> 2 | V72: =IFERROR(T72/H72,"") -> 0.33652297 | W72: =IFERROR(I72/H72,"") -> 0.31146187 | X72: =IF(M72="","",IFERROR(M72/D72,"")) -> 0.0064445644 | Y72: =IFERROR(RANK(P72,P$2:P$93),"") -> 50 | Z72: =IFERROR(RANK(Q72,Q$2:Q$93),"") -> 75 | AA72: =IFERROR(RANK(S72,S$2:S$93),"") -> 66 | AB72: =IF(U72>=2,COUNTIFS(U$2:U$93,">=2",V$2:V$93,">"&V72)+1,"n/c") -> 86
A73: Saquarema | B73: 3305505 | C73: 95201 | D73: 3.0651295e+09 | E73: 2.5615549e+09 | F73: 2.5615549e+09 | G73: 4.7535808e+08 | H73: 3.0170114e+09 | I73: 5.4898485e+08 | J73: 11937471 | K73: -1.0328 | M73: 5991646.5 | N73: não | P73: =IFERROR(G73/C73,"") -> 4993.2047 | Q73: =IFERROR(G73/F73,"") -> 0.18557404 | R73: =IFERROR(D73/C73,"") -> 32196.401 | S73: =IFERROR(E73/D73,"") -> 0.83570853 | T73: =SUM(I73:J73) -> 5.6092232e+08 | U73: =COUNT(I73:J73) -> 2 | V73: =IFERROR(T73/H73,"") -> 0.18591985 | W73: =IFERROR(I73/H73,"") -> 0.18196313 | X73: =IF(M73="","",IFERROR(M73/D73,"")) -> 0.0019547776 | Y73: =IFERROR(RANK(P73,P$2:P$93),"") -> 6 | Z73: =IFERROR(RANK(Q73,Q$2:Q$93),"") -> 89 | AA73: =IFERROR(RANK(S73,S$2:S$93),"") -> 92 | AB73: =IF(U73>=2,COUNTIFS(U$2:U$93,">=2",V$2:V$93,">"&V73)+1,"n/c") -> 90 | AC73: Sem limite de dívida declarado
A74: Seropédica | B74: 3305554 | C74: 84737 | D74: 4.8201713e+08 | E74: 5.1232896e+08 | F74: 5.1232896e+08 | G74: 1.3919896e+08 | H74: 4.5464027e+08 | I74: 2.9024448e+08 | J74: 10224851 | K74: -2.8575 | L74: 1.2 | M74: 73008765 | N74: não | P74: =IFERROR(G74/C74,"") -> 1642.7175 | Q74: =IFERROR(G74/F74,"") -> 0.27169839 | R74: =IFERROR(D74/C74,"") -> 5688.3903 | S74: =IFERROR(E74/D74,"") -> 1.0628854 | T74: =SUM(I74:J74) -> 3.0046933e+08 | U74: =COUNT(I74:J74) -> 2 | V74: =IFERROR(T74/H74,"") -> 0.66089468 | W74: =IFERROR(I74/H74,"") -> 0.6384047 | X74: =IF(M74="","",IFERROR(M74/D74,"")) -> 0.15146508 | Y74: =IFERROR(RANK(P74,P$2:P$93),"") -> 71 | Z74: =IFERROR(RANK(Q74,Q$2:Q$93),"") -> 55 | AA74: =IFERROR(RANK(S74,S$2:S$93),"") -> 27 | AB74: =IF(U74>=2,COUNTIFS(U$2:U$93,">=2",V$2:V$93,">"&V74)+1,"n/c") -> 3
A75: Silva Jardim | B75: 3305604 | C75: 22026 | D75: 3.3570992e+08 | E75: 3.3851843e+08 | F75: 3.3851843e+08 | G75: 86721310 | H75: 3.1988266e+08 | I75: 1.3050679e+08 | J75: 4843034 | K75: -0.2657 | L75: 1.2 | M75: 2939706.1 | N75: não | P75: =IFERROR(G75/C75,"") -> 3937.2246 | Q75: =IFERROR(G75/F75,"") -> 0.25617899 | R75: =IFERROR(D75/C75,"") -> 15241.529 | S75: =IFERROR(E75/D75,"") -> 1.0083659 | T75: =SUM(I75:J75) -> 1.3534982e+08 | U75: =COUNT(I75:J75) -> 2 | V75: =IFERROR(T75/H75,"") -> 0.42312335 | W75: =IFERROR(I75/H75,"") -> 0.40798332 | X75: =IF(M75="","",IFERROR(M75/D75,"")) -> 0.0087566854 | Y75: =IFERROR(RANK(P75,P$2:P$93),"") -> 9 | Z75: =IFERROR(RANK(Q75,Q$2:Q$93),"") -> 65 | AA75: =IFERROR(RANK(S75,S$2:S$93),"") -> 53 | AB75: =IF(U75>=2,COUNTIFS(U$2:U$93,">=2",V$2:V$93,">"&V75)+1,"n/c") -> 68
A76: Sumidouro | B76: 3305703 | C76: 15690 | D76: 1.3544211e+08 | E76: 1.3790784e+08 | F76: 1.3790784e+08 | G76: 42438983 | H76: 1.1391131e+08 | I76: 62145691 | J76: 2749796.5 | K76: -0.0991 | L76: 1.2 | M76: 1505813.6 | N76: não | P76: =IFERROR(G76/C76,"") -> 2704.8428 | Q76: =IFERROR(G76/F76,"") -> 0.30773439 | R76: =IFERROR(D76/C76,"") -> 8632.3844 | S76: =IFERROR(E76/D76,"") -> 1.018205 | T76: =SUM(I76:J76) -> 64895487 | U76: =COUNT(I76:J76) -> 2 | V76: =IFERROR(T76/H76,"") -> 0.56970189 | W76: =IFERROR(I76/H76,"") -> 0.54556209 | X76: =IF(M76="","",IFERROR(M76/D76,"")) -> 0.011117765 | Y76: =IFERROR(RANK(P76,P$2:P$93),"") -> 34 | Z76: =IFERROR(RANK(Q76,Q$2:Q$93),"") -> 34 | AA76: =IFERROR(RANK(S76,S$2:S$93),"") -> 48 | AB76: =IF(U76>=2,COUNTIFS(U$2:U$93,">=2",V$2:V$93,">"&V76)+1,"n/c") -> 8 | AC76: Limite de dívida declarado já como percentual
A77: São Fidélis | B77: 3304805 | C77: 41197 | D77: 2.1254307e+08 | E77: 2.2197832e+08 | F77: 2.2197832e+08 | G77: 59997523 | H77: 2.0255956e+08 | I77: 96102124 | J77: 4709036.6 | K77: 0.055 | L77: 1.2 | M77: 9391414.7 | N77: não | P77: =IFERROR(G77/C77,"") -> 1456.3566 | Q77: =IFERROR(G77/F77,"") -> 0.27028551 | R77: =IFERROR(D77/C77,"") -> 5159.1882 | S77: =IFERROR(E77/D77,"") -> 1.0443922 | T77: =SUM(I77:J77) -> 1.0081116e+08 | U77: =COUNT(I77:J77) -> 2 | V77: =IFERROR(T77/H77,"") -> 0.4976865 | W77: =IFERROR(I77/H77,"") -> 0.47443884 | X77: =IF(M77="","",IFERROR(M77/D77,"")) -> 0.044185936 | Y77: =IFERROR(RANK(P77,P$2:P$93),"") -> 77 | Z77: =IFERROR(RANK(Q77,Q$2:Q$93),"") -> 57 | AA77: =IFERROR(RANK(S77,S$2:S$93),"") -> 35 | AB77: =IF(U77>=2,COUNTIFS(U$2:U$93,">=2",V$2:V$93,">"&V77)+1,"n/c") -> 39 | AC77: Limite de dívida declarado já como percentual
A78: São Francisco de Itabapoana | B78: 3304755 | C78: 47368 | D78: 3.0522994e+08 | E78: 2.9757691e+08 | F78: 2.9975693e+08 | G78: 54724726 | H78: 3.0415922e+08 | I78: 1.616538e+08 | J78: 5581778.4 | K78: 0.0981 | L78: 1.2 | M78: 5560516.7 | N78: não | P78: =IFERROR(G78/C78,"") -> 1155.31 | Q78: =IFERROR(G78/F78,"") -> 0.18256367 | R78: =IFERROR(D78/C78,"") -> 6443.8006 | S78: =IFERROR(E78/D78,"") -> 0.97492697 | T78: =SUM(I78:J78) -> 1.6723558e+08 | U78: =COUNT(I78:J78) -> 2 | V78: =IFERROR(T78/H78,"") -> 0.54982908 | W78: =IFERROR(I78/H78,"") -> 0.53147758 | X78: =IF(M78="","",IFERROR(M78/D78,"")) -> 0.018217468 | Y78: =IFERROR(RANK(P78,P$2:P$93),"") -> 83 | Z78: =IFERROR(RANK(Q78,Q$2:Q$93),"") -> 90 | AA78: =IFERROR(RANK(S78,S$2:S$93),"") -> 73 | AB78: =IF(U78>=2,COUNTIFS(U$2:U$93,">=2",V$2:V$93,">"&V78)+1,"n/c") -> 15
A79: São Gonçalo | B79: 3304904 | C79: 960652 | D79: 2.5287995e+09 | E79: 2.6578557e+09 | F79: 2.6843626e+09 | G79: 1.0227445e+09 | H79: 2.4185809e+09 | I79: 9.6859503e+08 | J79: 27041543 | K79: 0.1641 | L79: 1.2 | M79: 50834910 | N79: não | P79: =IFERROR(G79/C79,"") -> 1064.6357 | Q79: =IFERROR(G79/F79,"") -> 0.38100087 | R79: =IFERROR(D79/C79,"") -> 2632.3784 | S79: =IFERROR(E79/D79,"") -> 1.0510346 | T79: =SUM(I79:J79) -> 9.9563657e+08 | U79: =COUNT(I79:J79) -> 2 | V79: =IFERROR(T79/H79,"") -> 0.41166146 | W79: =IFERROR(I79/H79,"") -> 0.40048072 | X79: =IF(M79="","",IFERROR(M79/D79,"")) -> 0.020102388 | Y79: =IFERROR(RANK(P79,P$2:P$93),"") -> 88 | Z79: =IFERROR(RANK(Q79,Q$2:Q$93),"") -> 4 | AA79: =IFERROR(RANK(S79,S$2:S$93),"") -> 30 | AB79: =IF(U79>=2,COUNTIFS(U$2:U$93,">=2",V$2:V$93,">"&V79)+1,"n/c") -> 71
A80: São José de Ubá | B80: 3305133 | C80: 7315 | D80: 89302691 | E80: 82651026 | F80: 82651026 | G80: 26077831 | H80: 75726891 | I80: 37829752 | J80: 2069982.3 | K80: -0.0752 | L80: 1.2 | M80: 574924.65 | N80: não | P80: =IFERROR(G80/C80,"") -> 3564.9804 | Q80: =IFERROR(G80/F80,"") -> 0.31551733 | R80: =IFERROR(D80/C80,"") -> 12208.16 | S80: =IFERROR(E80/D80,"") -> 0.92551552 | T80: =SUM(I80:J80) -> 39899735 | U80: =COUNT(I80:J80) -> 2 | V80: =IFERROR(T80/H80,"") -> 0.52688991 | W80: =IFERROR(I80/H80,"") -> 0.49955507 | X80: =IF(M80="","",IFERROR(M80/D80,"")) -> 0.006437932 | Y80: =IFERROR(RANK(P80,P$2:P$93),"") -> 17 | Z80: =IFERROR(RANK(Q80,Q$2:Q$93),"") -> 28 | AA80: =IFERROR(RANK(S80,S$2:S$93),"") -> 83 | AB80: =IF(U80>=2,COUNTIFS(U$2:U$93,">=2",V$2:V$93,">"&V80)+1,"n/c") -> 22
A81: São José do Vale do Rio Preto | B81: 3305158 | C81: 22799 | D81: 1.4089519e+08 | E81: 1.381931e+08 | F81: 1.381931e+08 | G81: 46699571 | H81: 1.3882431e+08 | I81: 64527658 | J81: 3447428.1 | K81: -0.1076 | L81: 1.2 | M81: 723315.86 | N81: não | P81: =IFERROR(G81/C81,"") -> 2048.3167 | Q81: =IFERROR(G81/F81,"") -> 0.33792982 | R81: =IFERROR(D81/C81,"") -> 6179.8847 | S81: =IFERROR(E81/D81,"") -> 0.980822 | T81: =SUM(I81:J81) -> 67975086 | U81: =COUNT(I81:J81) -> 2 | V81: =IFERROR(T81/H81,"") -> 0.4896483 | W81: =IFERROR(I81/H81,"") -> 0.46481527 | X81: =IF(M81="","",IFERROR(M81/D81,"")) -> 0.0051337157 | Y81: =IFERROR(RANK(P81,P$2:P$93),"") -> 58 | Z81: =IFERROR(RANK(Q81,Q$2:Q$93),"") -> 19 | AA81: =IFERROR(RANK(S81,S$2:S$93),"") -> 72 | AB81: =IF(U81>=2,COUNTIFS(U$2:U$93,">=2",V$2:V$93,">"&V81)+1,"n/c") -> 43
A82: São João da Barra | B82: 3305000 | C82: 38708 | D82: 9.2163872e+08 | E82: 9.9005561e+08 | F82: 9.9005561e+08 | G82: 2.5023936e+08 | H82: 8.7022609e+08 | I82: 3.7999801e+08 | J82: 9448549.6 | K82: -0.3371 | L82: 1.2 | M82: 16656627 | N82: não | P82: =IFERROR(G82/C82,"") -> 6464.7968 | Q82: =IFERROR(G82/F82,"") -> 0.25275283 | R82: =IFERROR(D82/C82,"") -> 23810.032 | S82: =IFERROR(E82/D82,"") -> 1.074234 | T82: =SUM(I82:J82) -> 3.8944656e+08 | U82: =COUNT(I82:J82) -> 2 | V82: =IFERROR(T82/H82,"") -> 0.44752342 | W82: =IFERROR(I82/H82,"") -> 0.43666584 | X82: =IF(M82="","",IFERROR(M82/D82,"")) -> 0.018072838 | Y82: =IFERROR(RANK(P82,P$2:P$93),"") -> 1 | Z82: =IFERROR(RANK(Q82,Q$2:Q$93),"") -> 68 | AA82: =IFERROR(RANK(S82,S$2:S$93),"") -> 24 | AB82: =IF(U82>=2,COUNTIFS(U$2:U$93,">=2",V$2:V$93,">"&V82)+1,"n/c") -> 57
A83: São João de Meriti | B83: 3305109 | C83: 466536 | D83: 1.2390544e+09 | E83: 1.2295991e+09 | F83: 1.2295991e+09 | G83: 4.1983042e+08 | H83: 1.0807288e+09 | I83: 5.8610443e+08 | J83: 17560974 | K83: 0.4341 | L83: 1.2 | M83: 2.1277723e+08 | N83: não | P83: =IFERROR(G83/C83,"") -> 899.88858 | Q83: =IFERROR(G83/F83,"") -> 0.34143682 | R83: =IFERROR(D83/C83,"") -> 2655.8602 | S83: =IFERROR(E83/D83,"") -> 0.99236896 | T83: =SUM(I83:J83) -> 6.036654e+08 | U83: =COUNT(I83:J83) -> 2 | V83: =IFERROR(T83/H83,"") -> 0.55857251 | W83: =IFERROR(I83/H83,"") -> 0.54232331 | X83: =IF(M83="","",IFERROR(M83/D83,"")) -> 0.1717255 | Y83: =IFERROR(RANK(P83,P$2:P$93),"") -> 92 | Z83: =IFERROR(RANK(Q83,Q$2:Q$93),"") -> 14 | AA83: =IFERROR(RANK(S83,S$2:S$93),"") -> 65 | AB83: =IF(U83>=2,COUNTIFS(U$2:U$93,">=2",V$2:V$93,">"&V83)+1,"n/c") -> 11
A84: São Pedro da Aldeia | B84: 3305208 | C84: 110556 | D84: 4.8555184e+08 | E84: 4.6541379e+08 | F84: 4.6541379e+08 | G84: 1.0494106e+08 | H84: 4.4747967e+08 | I84: 2.1410512e+08 | J84: 8646183.2 | K84: 0.1022 | L84: 1.2 | M84: 9080583.3 | N84: não | P84: =IFERROR(G84/C84,"") -> 949.21185 | Q84: =IFERROR(G84/F84,"") -> 0.22547906 | R84: =IFERROR(D84/C84,"") -> 4391.9085 | S84: =IFERROR(E84/D84,"") -> 0.95852544 | T84: =SUM(I84:J84) -> 2.2275131e+08 | U84: =COUNT(I84:J84) -> 2 | V84: =IFERROR(T84/H84,"") -> 0.4977909 | W84: =IFERROR(I84/H84,"") -> 0.47846894 | X84: =IF(M84="","",IFERROR(M84/D84,"")) -> 0.018701573 | Y84: =IFERROR(RANK(P84,P$2:P$93),"") -> 91 | Z84: =IFERROR(RANK(Q84,Q$2:Q$93),"") -> 83 | AA84: =IFERROR(RANK(S84,S$2:S$93),"") -> 77 | AB84: =IF(U84>=2,COUNTIFS(U$2:U$93,">=2",V$2:V$93,">"&V84)+1,"n/c") -> 38
A85: São Sebastião do Alto | B85: 3305307 | C85: 7999 | D85: 92942879 | E85: 96537986 | F85: 97157964 | G85: 24412114 | H85: 88923797 | I85: 53921638 | J85: 2845036.3 | K85: 0.0892 | L85: 1.2 | M85: 1315217.1 | N85: não | P85: =IFERROR(G85/C85,"") -> 3051.8958 | Q85: =IFERROR(G85/F85,"") -> 0.2512621 | R85: =IFERROR(D85/C85,"") -> 11619.312 | S85: =IFERROR(E85/D85,"") -> 1.0386808 | T85: =SUM(I85:J85) -> 56766674 | U85: =COUNT(I85:J85) -> 2 | V85: =IFERROR(T85/H85,"") -> 0.63837439 | W85: =IFERROR(I85/H85,"") -> 0.60638029 | X85: =IF(M85="","",IFERROR(M85/D85,"")) -> 0.014150811 | Y85: =IFERROR(RANK(P85,P$2:P$93),"") -> 28 | Z85: =IFERROR(RANK(Q85,Q$2:Q$93),"") -> 70 | AA85: =IFERROR(RANK(S85,S$2:S$93),"") -> 38 | AB85: =IF(U85>=2,COUNTIFS(U$2:U$93,">=2",V$2:V$93,">"&V85)+1,"n/c") -> 5
A86: Tanguá | B86: 3305752 | C86: 32858 | D86: 2.0612127e+08 | E86: 2.0700294e+08 | F86: 2.0700294e+08 | G86: 69222377 | H86: 1.8801413e+08 | I86: 79961074 | J86: 3684096.7 | K86: -0.1289 | L86: 1.2 | M86: 3827923.8 | N86: sim | P86: =IFERROR(G86/C86,"") -> 2106.713 | Q86: =IFERROR(G86/F86,"") -> 0.33440287 | R86: =IFERROR(D86/C86,"") -> 6273.0923 | S86: =IFERROR(E86/D86,"") -> 1.0042774 | T86: =SUM(I86:J86) -> 83645171 | U86: =COUNT(I86:J86) -> 2 | V86: =IFERROR(T86/H86,"") -> 0.44488768 | W86: =IFERROR(I86/H86,"") -> 0.4252929 | X86: =IF(M86="","",IFERROR(M86/D86,"")) -> 0.018571222 | Y86: =IFERROR(RANK(P86,P$2:P$93),"") -> 56 | Z86: =IFERROR(RANK(Q86,Q$2:Q$93),"") -> 20 | AA86: =IFERROR(RANK(S86,S$2:S$93),"") -> 57 | AB86: =IF(U86>=2,COUNTIFS(U$2:U$93,">=2",V$2:V$93,">"&V86)+1,"n/c") -> 59 | AC86: Relatório simplificado
A87: Teresópolis | B87: 3305802 | C87: 176692 | D87: 8.6990922e+08 | E87: 8.7657119e+08 | F87: 8.7657119e+08 | G87: 2.1495061e+08 | H87: 8.4291374e+08 | I87: 4.2039072e+08 | J87: 22007214 | K87: -0.1195 | L87: 1.2 | M87: 66421829 | N87: não | P87: =IFERROR(G87/C87,"") -> 1216.5271 | Q87: =IFERROR(G87/F87,"") -> 0.24521752 | R87: =IFERROR(D87/C87,"") -> 4923.3085 | S87: =IFERROR(E87/D87,"") -> 1.0076582 | T87: =SUM(I87:J87) -> 4.4239793e+08 | U87: =COUNT(I87:J87) -> 2 | V87: =IFERROR(T87/H87,"") -> 0.52484366 | W87: =IFERROR(I87/H87,"") -> 0.49873516 | X87: =IF(M87="","",IFERROR(M87/D87,"")) -> 0.076354898 | Y87: =IFERROR(RANK(P87,P$2:P$93),"") -> 82 | Z87: =IFERROR(RANK(Q87,Q$2:Q$93),"") -> 73 | AA87: =IFERROR(RANK(S87,S$2:S$93),"") -> 55 | AB87: =IF(U87>=2,COUNTIFS(U$2:U$93,">=2",V$2:V$93,">"&V87)+1,"n/c") -> 25
A88: Trajano de Moraes | B88: 3305901 | C88: 10652 | D88: 1.1070458e+08 | E88: 1.1105855e+08 | F88: 1.1105855e+08 | G88: 22276512 | H88: 97896192 | I88: 51564156 | J88: 3037461.1 | K88: 0.3759 | L88: 1.2 | M88: 6842.26 | N88: não | P88: =IFERROR(G88/C88,"") -> 2091.2985 | Q88: =IFERROR(G88/F88,"") -> 0.20058349 | R88: =IFERROR(D88/C88,"") -> 10392.844 | S88: =IFERROR(E88/D88,"") -> 1.0031974 | T88: =SUM(I88:J88) -> 54601617 | U88: =COUNT(I88:J88) -> 2 | V88: =IFERROR(T88/H88,"") -> 0.55775017 | W88: =IFERROR(I88/H88,"") -> 0.5267228 | X88: =IF(M88="","",IFERROR(M88/D88,"")) -> 6.1806477e-05 | Y88: =IFERROR(RANK(P88,P$2:P$93),"") -> 57 | Z88: =IFERROR(RANK(Q88,Q$2:Q$93),"") -> 87 | AA88: =IFERROR(RANK(S88,S$2:S$93),"") -> 58 | AB88: =IF(U88>=2,COUNTIFS(U$2:U$93,">=2",V$2:V$93,">"&V88)+1,"n/c") -> 12 | AC88: Limite de dívida declarado já como percentual
A89: Três Rios | B89: 3306008 | C89: 82300 | D89: 5.6259068e+08 | E89: 5.6304498e+08 | F89: 5.6304498e+08 | G89: 1.6399668e+08 | H89: 5.0681967e+08 | I89: 2.4733272e+08 | J89: 12803112 | K89: 0.0718 | L89: 1.2 | M89: 15210899 | N89: não | P89: =IFERROR(G89/C89,"") -> 1992.6692 | Q89: =IFERROR(G89/F89,"") -> 0.29126745 | R89: =IFERROR(D89/C89,"") -> 6835.8528 | S89: =IFERROR(E89/D89,"") -> 1.0008075 | T89: =SUM(I89:J89) -> 2.6013583e+08 | U89: =COUNT(I89:J89) -> 2 | V89: =IFERROR(T89/H89,"") -> 0.51327097 | W89: =IFERROR(I89/H89,"") -> 0.4880093 | X89: =IF(M89="","",IFERROR(M89/D89,"")) -> 0.027037239 | Y89: =IFERROR(RANK(P89,P$2:P$93),"") -> 59 | Z89: =IFERROR(RANK(Q89,Q$2:Q$93),"") -> 46 | AA89: =IFERROR(RANK(S89,S$2:S$93),"") -> 59 | AB89: =IF(U89>=2,COUNTIFS(U$2:U$93,">=2",V$2:V$93,">"&V89)+1,"n/c") -> 30
A90: Valença | B90: 3306107 | C90: 71462 | D90: 3.9162595e+08 | E90: 3.9672018e+08 | F90: 3.9672018e+08 | G90: 1.188651e+08 | H90: 3.4794253e+08 | I90: 1.7975742e+08 | J90: 5786327.7 | K90: -0.1745 | L90: 1.2 | M90: 15582050 | N90: não | P90: =IFERROR(G90/C90,"") -> 1663.3329 | Q90: =IFERROR(G90/F90,"") -> 0.2996195 | R90: =IFERROR(D90/C90,"") -> 5480.1985 | S90: =IFERROR(E90/D90,"") -> 1.0130079 | T90: =SUM(I90:J90) -> 1.8554375e+08 | U90: =COUNT(I90:J90) -> 2 | V90: =IFERROR(T90/H90,"") -> 0.53325977 | W90: =IFERROR(I90/H90,"") -> 0.51662964 | X90: =IF(M90="","",IFERROR(M90/D90,"")) -> 0.039788094 | Y90: =IFERROR(RANK(P90,P$2:P$93),"") -> 70 | Z90: =IFERROR(RANK(Q90,Q$2:Q$93),"") -> 43 | AA90: =IFERROR(RANK(S90,S$2:S$93),"") -> 51 | AB90: =IF(U90>=2,COUNTIFS(U$2:U$93,">=2",V$2:V$93,">"&V90)+1,"n/c") -> 20
A91: Varre-Sai | B91: 3306156 | C91: 10559 | D91: 1.0052624e+08 | E91: 96376200 | F91: 96376200 | G91: 25294037 | H91: 88110939 | I91: 42391787 | J91: 2694039.1 | K91: -0.0669 | L91: 1.2 | M91: 2548288.9 | N91: não | P91: =IFERROR(G91/C91,"") -> 2395.4955 | Q91: =IFERROR(G91/F91,"") -> 0.26245107 | R91: =IFERROR(D91/C91,"") -> 9520.4321 | S91: =IFERROR(E91/D91,"") -> 0.95871682 | T91: =SUM(I91:J91) -> 45085826 | U91: =COUNT(I91:J91) -> 2 | V91: =IFERROR(T91/H91,"") -> 0.51169385 | W91: =IFERROR(I91/H91,"") -> 0.48111832 | X91: =IF(M91="","",IFERROR(M91/D91,"")) -> 0.025349489 | Y91: =IFERROR(RANK(P91,P$2:P$93),"") -> 45 | Z91: =IFERROR(RANK(Q91,Q$2:Q$93),"") -> 60 | AA91: =IFERROR(RANK(S91,S$2:S$93),"") -> 76 | AB91: =IF(U91>=2,COUNTIFS(U$2:U$93,">=2",V$2:V$93,">"&V91)+1,"n/c") -> 31
A92: Vassouras | B92: 3306206 | C92: 35904 | D92: 2.9865534e+08 | E92: 3.1034265e+08 | F92: 3.1034265e+08 | G92: 1.3862223e+08 | H92: 2.5046168e+08 | I92: 1.2297763e+08 | J92: 5139194.2 | K92: 0.2886 | M92: 9948620.2 | N92: sim | P92: =IFERROR(G92/C92,"") -> 3860.9134 | Q92: =IFERROR(G92/F92,"") -> 0.44667478 | R92: =IFERROR(D92/C92,"") -> 8318.1634 | S92: =IFERROR(E92/D92,"") -> 1.0391331 | T92: =SUM(I92:J92) -> 1.2811683e+08 | U92: =COUNT(I92:J92) -> 2 | V92: =IFERROR(T92/H92,"") -> 0.51152266 | W92: =IFERROR(I92/H92,"") -> 0.49100378 | X92: =IF(M92="","",IFERROR(M92/D92,"")) -> 0.033311375 | Y92: =IFERROR(RANK(P92,P$2:P$93),"") -> 10 | Z92: =IFERROR(RANK(Q92,Q$2:Q$93),"") -> 3 | AA92: =IFERROR(RANK(S92,S$2:S$93),"") -> 37 | AB92: =IF(U92>=2,COUNTIFS(U$2:U$93,">=2",V$2:V$93,">"&V92)+1,"n/c") -> 32 | AC92: Relatório simplificado; Sem limite de dívida declarado
A93: Volta Redonda | B93: 3306305 | C93: 279898 | D93: 1.8762265e+09 | E93: 1.7731106e+09 | F93: 1.7731106e+09 | G93: 5.4497897e+08 | H93: 1.71421e+09 | I93: 5.3714373e+08 | J93: 38234405 | K93: 0.0691 | L93: 1.2 | M93: 63933346 | N93: não | P93: =IFERROR(G93/C93,"") -> 1947.0627 | Q93: =IFERROR(G93/F93,"") -> 0.30735756 | R93: =IFERROR(D93/C93,"") -> 6703.2509 | S93: =IFERROR(E93/D93,"") -> 0.94504082 | T93: =SUM(I93:J93) -> 5.7537813e+08 | U93: =COUNT(I93:J93) -> 2 | V93: =IFERROR(T93/H93,"") -> 0.33565208 | W93: =IFERROR(I93/H93,"") -> 0.31334769 | X93: =IF(M93="","",IFERROR(M93/D93,"")) -> 0.034075494 | Y93: =IFERROR(RANK(P93,P$2:P$93),"") -> 64 | Z93: =IFERROR(RANK(Q93,Q$2:Q$93),"") -> 36 | AA93: =IFERROR(RANK(S93,S$2:S$93),"") -> 80 | AB93: =IF(U93>=2,COUNTIFS(U$2:U$93,">=2",V$2:V$93,">"&V93)+1,"n/c") -> 88

Sheet Com e sem
A1: Resultados com e sem os casos especiais (municípios do RJ)
A2: Mediana de cada indicador em quatro versões: todos os municípios; sem os 4 de dado atípico; sem os 12 de relatório simplificado; sem os dois grupos. Tudo é fórmula sobre a aba 'Municípios RJ'. Os 4 atípicos são os marcados em amarelo naquela aba.
A4: Versão | B4: nº de municípios | C4: Saúde por habitante (mediana) | D4: Saúde, % da despesa (mediana) | E4: Pessoal total, % da RCL (mediana) | F4: Despesa, % da receita (mediana)
A5: Todos os municípios | B5: =COUNT('Municípios RJ'!P2:P93) -> 92 | C5: =MEDIAN('Municípios RJ'!P2:P93) -> 2319.4488 | D5: =MEDIAN('Municípios RJ'!Q2:Q93) -> 0.28996425 | E5: =MEDIAN('Municípios RJ'!V2:V93) -> 0.48144483 | F5: =MEDIAN('Municípios RJ'!S2:S93) -> 1.0214342
A6: Sem os 4 de dado atípico | B6: =COUNT(D12:D103) -> 88 | C6: =MEDIAN(D12:D103) -> 2282.0391 | D6: =MEDIAN(G12:G103) -> 0.29340896 | E6: =MEDIAN(J12:J103) -> 0.46728645 | F6: =MEDIAN(M12:M103) -> 1.0195663
A7: Sem os 12 simplificados | B7: =COUNT(E12:E103) -> 80 | C7: =MEDIAN(E12:E103) -> 2225.1764 | D7: =MEDIAN(H12:H103) -> 0.28503176 | E7: =MEDIAN(K12:K103) -> 0.48814696 | F7: =MEDIAN(N12:N103) -> 1.0223343
A8: Sem os atípicos e sem os simplificados | B8: =COUNT(F12:F103) -> 76 | C8: =MEDIAN(F12:F103) -> 2209.6754 | D8: =MEDIAN(I12:I103) -> 0.28503176 | E8: =MEDIAN(L12:L103) -> 0.47259841 | F8: =MEDIAN(O12:O103) -> 1.0200729
A10: Bloco auxiliar (alimenta as medianas acima): cada coluna repete o indicador só para os municípios que ficam na versão.
A11: Município | B11: Caso especial | C11: Simplificado? | D11: Saúde por habitante | sem atípicos | E11: Saúde por habitante | sem simplificados | F11: Saúde por habitante | sem ambos | G11: Saúde, % da despesa | sem atípicos | H11: Saúde, % da despesa | sem simplificados | I11: Saúde, % da despesa | sem ambos | J11: Pessoal total, % da RCL | sem atípicos | K11: Pessoal total, % da RCL | sem simplificados | L11: Pessoal total, % da RCL | sem ambos | M11: Despesa, % da receita | sem atípicos | N11: Despesa, % da receita | sem simplificados | O11: Despesa, % da receita | sem ambos
A12: ='Municípios RJ'!A2 -> Angra dos Reis | B12: ='Municípios RJ'!O2&"" | C12: ='Municípios RJ'!N2 -> não | D12: =IF($B12="",'Municípios RJ'!P2,"") -> 3792.5879 | E12: =IF($C12="não",'Municípios RJ'!P2,"") -> 3792.5879 | F12: =IF(AND($B12="",$C12="não"),'Municípios RJ'!P2,"") -> 3792.5879 | G12: =IF($B12="",'Municípios RJ'!Q2,"") -> 0.25570148 | H12: =IF($C12="não",'Municípios RJ'!Q2,"") -> 0.25570148 | I12: =IF(AND($B12="",$C12="não"),'Municípios RJ'!Q2,"") -> 0.25570148 | J12: =IF($B12="",'Municípios RJ'!V2,"") -> 0.45994444 | K12: =IF($C12="não",'Municípios RJ'!V2,"") -> 0.45994444 | L12: =IF(AND($B12="",$C12="não"),'Municípios RJ'!V2,"") -> 0.45994444 | M12: =IF($B12="",'Municípios RJ'!S2,"") -> 1.136949 | N12: =IF($C12="não",'Municípios RJ'!S2,"") -> 1.136949 | O12: =IF(AND($B12="",$C12="não"),'Municípios RJ'!S2,"") -> 1.136949
A13: ='Municípios RJ'!A3 -> Aperibé | B13: ='Municípios RJ'!O3&"" | C13: ='Municípios RJ'!N3 -> não | D13: =IF($B13="",'Municípios RJ'!P3,"") -> 3035.1443 | E13: =IF($C13="não",'Municípios RJ'!P3,"") -> 3035.1443 | F13: =IF(AND($B13="",$C13="não"),'Municípios RJ'!P3,"") -> 3035.1443 | G13: =IF($B13="",'Municípios RJ'!Q3,"") -> 0.31218798 | H13: =IF($C13="não",'Municípios RJ'!Q3,"") -> 0.31218798 | I13: =IF(AND($B13="",$C13="não"),'Municípios RJ'!Q3,"") -> 0.31218798 | J13: =IF($B13="",'Municípios RJ'!V3,"") -> 0.52659987 | K13: =IF($C13="não",'Municípios RJ'!V3,"") -> 0.52659987 | L13: =IF(AND($B13="",$C13="não"),'Municípios RJ'!V3,"") -> 0.52659987 | M13: =IF($B13="",'Municípios RJ'!S3,"") -> 0.93536698 | N13: =IF($C13="não",'Municípios RJ'!S3,"") -> 0.93536698 | O13: =IF(AND($B13="",$C13="não"),'Municípios RJ'!S3,"") -> 0.93536698
A14: ='Municípios RJ'!A4 -> Araruama | B14: ='Municípios RJ'!O4&"" | C14: ='Municípios RJ'!N4 -> não | D14: =IF($B14="",'Municípios RJ'!P4,"") -> 1959.9015 | E14: =IF($C14="não",'Municípios RJ'!P4,"") -> 1959.9015 | F14: =IF(AND($B14="",$C14="não"),'Municípios RJ'!P4,"") -> 1959.9015 | G14: =IF($B14="",'Municípios RJ'!Q4,"") -> 0.22810092 | H14: =IF($C14="não",'Municípios RJ'!Q4,"") -> 0.22810092 | I14: =IF(AND($B14="",$C14="não"),'Municípios RJ'!Q4,"") -> 0.22810092 | J14: =IF($B14="",'Municípios RJ'!V4,"") -> 0.35707737 | K14: =IF($C14="não",'Municípios RJ'!V4,"") -> 0.35707737 | L14: =IF(AND($B14="",$C14="não"),'Municípios RJ'!V4,"") -> 0.35707737 | M14: =IF($B14="",'Municípios RJ'!S4,"") -> 1.0227277 | N14: =IF($C14="não",'Municípios RJ'!S4,"") -> 1.0227277 | O14: =IF(AND($B14="",$C14="não"),'Municípios RJ'!S4,"") -> 1.0227277
A15: ='Municípios RJ'!A5 -> Areal | B15: ='Municípios RJ'!O5&"" -> RCL atípica | C15: ='Municípios RJ'!N5 -> não | D15: =IF($B15="",'Municípios RJ'!P5,"") | E15: =IF($C15="não",'Municípios RJ'!P5,"") -> 2835.1086 | F15: =IF(AND($B15="",$C15="não"),'Municípios RJ'!P5,"") | G15: =IF($B15="",'Municípios RJ'!Q5,"") | H15: =IF($C15="não",'Municípios RJ'!Q5,"") -> 0.23322259 | I15: =IF(AND($B15="",$C15="não"),'Municípios RJ'!Q5,"") | J15: =IF($B15="",'Municípios RJ'!V5,"") | K15: =IF($C15="não",'Municípios RJ'!V5,"") -> 1.5972773 | L15: =IF(AND($B15="",$C15="não"),'Municípios RJ'!V5,"") | M15: =IF($B15="",'Municípios RJ'!S5,"") | N15: =IF($C15="não",'Municípios RJ'!S5,"") -> 1.0316167 | O15: =IF(AND($B15="",$C15="não"),'Municípios RJ'!S5,"")
A16: ='Municípios RJ'!A6 -> Armação dos Búzios | B16: ='Municípios RJ'!O6&"" -> totais de despesa inconsistentes | C16: ='Municípios RJ'!N6 -> não | D16: =IF($B16="",'Municípios RJ'!P6,"") | E16: =IF($C16="não",'Municípios RJ'!P6,"") -> 3681.2006 | F16: =IF(AND($B16="",$C16="não"),'Municípios RJ'!P6,"") | G16: =IF($B16="",'Municípios RJ'!Q6,"") | H16: =IF($C16="não",'Municípios RJ'!Q6,"") -> 0.28790844 | I16: =IF(AND($B16="",$C16="não"),'Municípios RJ'!Q6,"") | J16: =IF($B16="",'Municípios RJ'!V6,"") | K16: =IF($C16="não",'Municípios RJ'!V6,"") -> 0.48816235 | L16: =IF(AND($B16="",$C16="não"),'Municípios RJ'!V6,"") | M16: =IF($B16="",'Municípios RJ'!S6,"") | N16: =IF($C16="não",'Municípios RJ'!S6,"") -> 0.85805589 | O16: =IF(AND($B16="",$C16="não"),'Municípios RJ'!S6,"")
A17: ='Municípios RJ'!A7 -> Arraial do Cabo | B17: ='Municípios RJ'!O7&"" | C17: ='Municípios RJ'!N7 -> não | D17: =IF($B17="",'Municípios RJ'!P7,"") -> 5524.553 | E17: =IF($C17="não",'Municípios RJ'!P7,"") -> 5524.553 | F17: =IF(AND($B17="",$C17="não"),'Municípios RJ'!P7,"") -> 5524.553 | G17: =IF($B17="",'Municípios RJ'!Q7,"") -> 0.25275737 | H17: =IF($C17="não",'Municípios RJ'!Q7,"") -> 0.25275737 | I17: =IF(AND($B17="",$C17="não"),'Municípios RJ'!Q7,"") -> 0.25275737 | J17: =IF($B17="",'Municípios RJ'!V7,"") -> 0.41830668 | K17: =IF($C17="não",'Municípios RJ'!V7,"") -> 0.41830668 | L17: =IF(AND($B17="",$C17="não"),'Municípios RJ'!V7,"") -> 0.41830668 | M17: =IF($B17="",'Municípios RJ'!S7,"") -> 0.87533714 | N17: =IF($C17="não",'Municípios RJ'!S7,"") -> 0.87533714 | O17: =IF(AND($B17="",$C17="não"),'Municípios RJ'!S7,"") -> 0.87533714
A18: ='Municípios RJ'!A8 -> Barra Mansa | B18: ='Municípios RJ'!O8&"" | C18: ='Municípios RJ'!N8 -> não | D18: =IF($B18="",'Municípios RJ'!P8,"") -> 1421.3956 | E18: =IF($C18="não",'Municípios RJ'!P8,"") -> 1421.3956 | F18: =IF(AND($B18="",$C18="não"),'Municípios RJ'!P8,"") -> 1421.3956 | G18: =IF($B18="",'Municípios RJ'!Q8,"") -> 0.27569681 | H18: =IF($C18="não",'Municípios RJ'!Q8,"") -> 0.27569681 | I18: =IF(AND($B18="",$C18="não"),'Municípios RJ'!Q8,"") -> 0.27569681 | J18: =IF($B18="",'Municípios RJ'!V8,"") -> 0.50263715 | K18: =IF($C18="não",'Municípios RJ'!V8,"") -> 0.50263715 | L18: =IF(AND($B18="",$C18="não"),'Municípios RJ'!V8,"") -> 0.50263715 | M18: =IF($B18="",'Municípios RJ'!S8,"") -> 1.0436582 | N18: =IF($C18="não",'Municípios RJ'!S8,"") -> 1.0436582 | O18: =IF(AND($B18="",$C18="não"),'Municípios RJ'!S8,"") -> 1.0436582
A19: ='Municípios RJ'!A9 -> Barra do Piraí | B19: ='Municípios RJ'!O9&"" | C19: ='Municípios RJ'!N9 -> não | D19: =IF($B19="",'Municípios RJ'!P9,"") -> 1273.9714 | E19: =IF($C19="não",'Municípios RJ'!P9,"") -> 1273.9714 | F19: =IF(AND($B19="",$C19="não"),'Municípios RJ'!P9,"") -> 1273.9714 | G19: =IF($B19="",'Municípios RJ'!Q9,"") -> 0.24857022 | H19: =IF($C19="não",'Municípios RJ'!Q9,"") -> 0.24857022 | I19: =IF(AND($B19="",$C19="não"),'Municípios RJ'!Q9,"") -> 0.24857022 | J19: =IF($B19="",'Municípios RJ'!V9,"") -> 0.45387495 | K19: =IF($C19="não",'Municípios RJ'!V9,"") -> 0.45387495 | L19: =IF(AND($B19="",$C19="não"),'Municípios RJ'!V9,"") -> 0.45387495 | M19: =IF($B19="",'Municípios RJ'!S9,"") -> 1.2207285 | N19: =IF($C19="não",'Municípios RJ'!S9,"") -> 1.2207285 | O19: =IF(AND($B19="",$C19="não"),'Municípios RJ'!S9,"") -> 1.2207285
A20: ='Municípios RJ'!A10 -> Belford Roxo | B20: ='Municípios RJ'!O10&"" | C20: ='Municípios RJ'!N10 -> não | D20: =IF($B20="",'Municípios RJ'!P10,"") -> 1101.6578 | E20: =IF($C20="não",'Municípios RJ'!P10,"") -> 1101.6578 | F20: =IF(AND($B20="",$C20="não"),'Municípios RJ'!P10,"") -> 1101.6578 | G20: =IF($B20="",'Municípios RJ'!Q10,"") -> 0.33981502 | H20: =IF($C20="não",'Municípios RJ'!Q10,"") -> 0.33981502 | I20: =IF(AND($B20="",$C20="não"),'Municípios RJ'!Q10,"") -> 0.33981502 | J20: =IF($B20="",'Municípios RJ'!V10,"") -> 0.51122668 | K20: =IF($C20="não",'Municípios RJ'!V10,"") -> 0.51122668 | L20: =IF(AND($B20="",$C20="não"),'Municípios RJ'!V10,"") -> 0.51122668 | M20: =IF($B20="",'Municípios RJ'!S10,"") -> 1.0277771 | N20: =IF($C20="não",'Municípios RJ'!S10,"") -> 1.0277771 | O20: =IF(AND($B20="",$C20="não"),'Municípios RJ'!S10,"") -> 1.0277771
A21: ='Municípios RJ'!A11 -> Bom Jardim | B21: ='Municípios RJ'!O11&"" | C21: ='Municípios RJ'!N11 -> não | D21: =IF($B21="",'Municípios RJ'!P11,"") -> 1478.6953 | E21: =IF($C21="não",'Municípios RJ'!P11,"") -> 1478.6953 | F21: =IF(AND($B21="",$C21="não"),'Municípios RJ'!P11,"") -> 1478.6953 | G21: =IF($B21="",'Municípios RJ'!Q11,"") -> 0.2867155 | H21: =IF($C21="não",'Municípios RJ'!Q11,"") -> 0.2867155 | I21: =IF(AND($B21="",$C21="não"),'Municípios RJ'!Q11,"") -> 0.2867155 | J21: =IF($B21="",'Municípios RJ'!V11,"") -> 0.51948019 | K21: =IF($C21="não",'Municípios RJ'!V11,"") -> 0.51948019 | L21: =IF(AND($B21="",$C21="não"),'Municípios RJ'!V11,"") -> 0.51948019 | M21: =IF($B21="",'Municípios RJ'!S11,"") -> 0.93580741 | N21: =IF($C21="não",'Municípios RJ'!S11,"") -> 0.93580741 | O21: =IF(AND($B21="",$C21="não"),'Municípios RJ'!S11,"") -> 0.93580741
A22: ='Municípios RJ'!A12 -> Bom Jesus do Itabapoana | B22: ='Municípios RJ'!O12&"" | C22: ='Municípios RJ'!N12 -> não | D22: =IF($B22="",'Municípios RJ'!P12,"") -> 3801.1149 | E22: =IF($C22="não",'Municípios RJ'!P12,"") -> 3801.1149 | F22: =IF(AND($B22="",$C22="não"),'Municípios RJ'!P12,"") -> 3801.1149 | G22: =IF($B22="",'Municípios RJ'!Q12,"") -> 0.47915152 | H22: =IF($C22="não",'Municípios RJ'!Q12,"") -> 0.47915152 | I22: =IF(AND($B22="",$C22="não"),'Municípios RJ'!Q12,"") -> 0.47915152 | J22: =IF($B22="",'Municípios RJ'!V12,"") -> 0.34561202 | K22: =IF($C22="não",'Municípios RJ'!V12,"") -> 0.34561202 | L22: =IF(AND($B22="",$C22="não"),'Municípios RJ'!V12,"") -> 0.34561202 | M22: =IF($B22="",'Municípios RJ'!S12,"") -> 1.0449895 | N22: =IF($C22="não",'Municípios RJ'!S12,"") -> 1.0449895 | O22: =IF(AND($B22="",$C22="não"),'Municípios RJ'!S12,"") -> 1.0449895
A23: ='Municípios RJ'!A13 -> Cabo Frio | B23: ='Municípios RJ'!O13&"" | C23: ='Municípios RJ'!N13 -> não | D23: =IF($B23="",'Municípios RJ'!P13,"") -> 1986.71 | E23: =IF($C23="não",'Municípios RJ'!P13,"") -> 1986.71 | F23: =IF(AND($B23="",$C23="não"),'Municípios RJ'!P13,"") -> 1986.71 | G23: =IF($B23="",'Municípios RJ'!Q13,"") -> 0.30227923 | H23: =IF($C23="não",'Municípios RJ'!Q13,"") -> 0.30227923 | I23: =IF(AND($B23="",$C23="não"),'Municípios RJ'!Q13,"") -> 0.30227923 | J23: =IF($B23="",'Municípios RJ'!V13,"") -> 0.64072167 | K23: =IF($C23="não",'Municípios RJ'!V13,"") -> 0.64072167 | L23: =IF(AND($B23="",$C23="não"),'Municípios RJ'!V13,"") -> 0.64072167 | M23: =IF($B23="",'Municípios RJ'!S13,"") -> 1.063921 | N23: =IF($C23="não",'Municípios RJ'!S13,"") -> 1.063921 | O23: =IF(AND($B23="",$C23="não"),'Municípios RJ'!S13,"") -> 1.063921
... A103: ='Municípios RJ'!A93 -> Volta Redonda | B103: ='Municípios RJ'!O93&"" | C103: ='Municípios RJ'!N93 -> não | D103: =IF($B103="",'Municípios RJ'!P93,"") -> 1947.0627 | E103: =IF($C103="não",'Municípios RJ'!P93,"") -> 1947.0627 | F103: =IF(AND($B103="",$C103="não"),'Municípios RJ'!P93,"") -> 1947.0627 | G103: =IF($B103="",'Municípios RJ'!Q93,"") -> 0.30735756 | H103: =IF($C103="não",'Municípios RJ'!Q93,"") -> 0.30735756 | I103: =IF(AND($B103="",$C103="não"),'Municípios RJ'!Q93,"") -> 0.30735756 | J103: =IF($B103="",'Municípios RJ'!V93,"") -> 0.33565208 | K103: =IF($C103="não",'Municípios RJ'!V93,"") -> 0.33565208 | L103: =IF(AND($B103="",$C103="não"),'Municípios RJ'!V93,"") -> 0.33565208 | M103: =IF($B103="",'Municípios RJ'!S93,"") -> 0.94504082 | N103: =IF($C103="não",'Municípios RJ'!S93,"") -> 0.94504082 | O103: =IF(AND($B103="",$C103="não"),'Municípios RJ'!S93,"") -> 0.94504082

Sheet Dados dos gráficos
A1: Dados que alimentam os gráficos. Os nomes estão na ordem do valor (maior primeiro) no momento da geração; os valores são fórmulas sobre a aba 'Estados'. Se os dados mudarem, a ordem pode ficar desatualizada.
A3: Estado | B3: Gasto em Saúde por habitante | D3: Estado | E3: Saúde como % da despesa total | G3: Estado | H3: Pessoal total (soma dos Poderes) | J3: Estado | K3: Dívida consolidada líquida
A4: Amapá | B4: =INDEX(Estados!$Q$2:$Q$28,MATCH(A4,Estados!$A$2:$A$28,0)) -> 2666.355 | D4: Tocantins | E4: =INDEX(Estados!$R$2:$R$28,MATCH(D4,Estados!$A$2:$A$28,0)) -> 0.22266026 | G4: Rio Grande do Norte | H4: =INDEX(Estados!$W$2:$W$28,MATCH(G4,Estados!$A$2:$A$28,0)) -> 0.66637402 | J4: Rio de Janeiro (estado) | K4: =INDEX(Estados!$N$2:$N$28,MATCH(J4,Estados!$A$2:$A$28,0)) -> 2.1132
A5: Acre | B5: =INDEX(Estados!$Q$2:$Q$28,MATCH(A5,Estados!$A$2:$A$28,0)) -> 2366.7283 | D5: Amapá | E5: =INDEX(Estados!$R$2:$R$28,MATCH(D5,Estados!$A$2:$A$28,0)) -> 0.21986278 | G5: Minas Gerais | H5: =INDEX(Estados!$W$2:$W$28,MATCH(G5,Estados!$A$2:$A$28,0)) -> 0.57329655 | J5: Rio Grande do Sul | K5: =INDEX(Estados!$N$2:$N$28,MATCH(J5,Estados!$A$2:$A$28,0)) -> 1.8467
A6: Tocantins | B6: =INDEX(Estados!$Q$2:$Q$28,MATCH(A6,Estados!$A$2:$A$28,0)) -> 2298.8683 | D6: Pernambuco | E6: =INDEX(Estados!$R$2:$R$28,MATCH(D6,Estados!$A$2:$A$28,0)) -> 0.20826084 | G6: Paraíba | H6: =INDEX(Estados!$W$2:$W$28,MATCH(G6,Estados!$A$2:$A$28,0)) -> 0.56384134 | J6: Minas Gerais | K6: =INDEX(Estados!$N$2:$N$28,MATCH(J6,Estados!$A$2:$A$28,0)) -> 1.6259
A7: Roraima | B7: =INDEX(Estados!$Q$2:$Q$28,MATCH(A7,Estados!$A$2:$A$28,0)) -> 2241.4389 | D7: Sergipe | E7: =INDEX(Estados!$R$2:$R$28,MATCH(D7,Estados!$A$2:$A$28,0)) -> 0.19965718 | G7: Roraima | H7: =INDEX(Estados!$W$2:$W$28,MATCH(G7,Estados!$A$2:$A$28,0)) -> 0.54610781 | J7: São Paulo | K7: =INDEX(Estados!$N$2:$N$28,MATCH(J7,Estados!$A$2:$A$28,0)) -> 1.2655
A8: Distrito Federal | B8: =INDEX(Estados!$Q$2:$Q$28,MATCH(A8,Estados!$A$2:$A$28,0)) -> 1752.9909 | D8: Roraima | E8: =INDEX(Estados!$R$2:$R$28,MATCH(D8,Estados!$A$2:$A$28,0)) -> 0.19764793 | G8: Rio de Janeiro (estado) | H8: =INDEX(Estados!$W$2:$W$28,MATCH(G8,Estados!$A$2:$A$28,0)) -> 0.54300628 | J8: Alagoas | K8: =INDEX(Estados!$N$2:$N$28,MATCH(J8,Estados!$A$2:$A$28,0)) -> 0.758
A9: Rondônia | B9: =INDEX(Estados!$Q$2:$Q$28,MATCH(A9,Estados!$A$2:$A$28,0)) -> 1354.5502 | D9: Bahia | E9: =INDEX(Estados!$R$2:$R$28,MATCH(D9,Estados!$A$2:$A$28,0)) -> 0.19313717 | G9: Acre | H9: =INDEX(Estados!$W$2:$W$28,MATCH(G9,Estados!$A$2:$A$28,0)) -> 0.53590858 | J9: Piauí | K9: =INDEX(Estados!$N$2:$N$28,MATCH(J9,Estados!$A$2:$A$28,0)) -> 0.6272
A10: Sergipe | B10: =INDEX(Estados!$Q$2:$Q$28,MATCH(A10,Estados!$A$2:$A$28,0)) -> 1297.1935 | D10: Acre | E10: =INDEX(Estados!$R$2:$R$28,MATCH(D10,Estados!$A$2:$A$28,0)) -> 0.18498307 | G10: Mato Grosso do Sul | H10: =INDEX(Estados!$W$2:$W$28,MATCH(G10,Estados!$A$2:$A$28,0)) -> 0.52886746 | J10: Rio Grande do Norte | K10: =INDEX(Estados!$N$2:$N$28,MATCH(J10,Estados!$A$2:$A$28,0)) -> 0.4018
A11: Espírito Santo | B11: =INDEX(Estados!$Q$2:$Q$28,MATCH(A11,Estados!$A$2:$A$28,0)) -> 1257.2292 | D11: Espírito Santo | E11: =INDEX(Estados!$R$2:$R$28,MATCH(D11,Estados!$A$2:$A$28,0)) -> 0.18467114 | G11: Tocantins | H11: =INDEX(Estados!$W$2:$W$28,MATCH(G11,Estados!$A$2:$A$28,0)) -> 0.52591829 | J11: Bahia | K11: =INDEX(Estados!$N$2:$N$28,MATCH(J11,Estados!$A$2:$A$28,0)) -> 0.371
A12: Amazonas | B12: =INDEX(Estados!$Q$2:$Q$28,MATCH(A12,Estados!$A$2:$A$28,0)) -> 1206.5745 | D12: Ceará | E12: =INDEX(Estados!$R$2:$R$28,MATCH(D12,Estados!$A$2:$A$28,0)) -> 0.17198311 | G12: Amapá | H12: =INDEX(Estados!$W$2:$W$28,MATCH(G12,Estados!$A$2:$A$28,0)) -> 0.50324924 | J12: Ceará | K12: =INDEX(Estados!$N$2:$N$28,MATCH(J12,Estados!$A$2:$A$28,0)) -> 0.3306
A13: Mato Grosso | B13: =INDEX(Estados!$Q$2:$Q$28,MATCH(A13,Estados!$A$2:$A$28,0)) -> 1109.7873 | D13: Maranhão | E13: =INDEX(Estados!$R$2:$R$28,MATCH(D13,Estados!$A$2:$A$28,0)) -> 0.17027439 | G13: Ceará | H13: =INDEX(Estados!$W$2:$W$28,MATCH(G13,Estados!$A$2:$A$28,0)) -> 0.49818227 | J13: Pernambuco | K13: =INDEX(Estados!$N$2:$N$28,MATCH(J13,Estados!$A$2:$A$28,0)) -> 0.3007
A14: Pernambuco | B14: =INDEX(Estados!$Q$2:$Q$28,MATCH(A14,Estados!$A$2:$A$28,0)) -> 1008.0849 | D14: Paraíba | E14: =INDEX(Estados!$R$2:$R$28,MATCH(D14,Estados!$A$2:$A$28,0)) -> 0.16507196 | G14: Goiás | H14: =INDEX(Estados!$W$2:$W$28,MATCH(G14,Estados!$A$2:$A$28,0)) -> 0.49704858 | J14: Amazonas | K14: =INDEX(Estados!$N$2:$N$28,MATCH(J14,Estados!$A$2:$A$28,0)) -> 0.2968
A15: Piauí | B15: =INDEX(Estados!$Q$2:$Q$28,MATCH(A15,Estados!$A$2:$A$28,0)) -> 1002.4516 | D15: Santa Catarina | E15: =INDEX(Estados!$R$2:$R$28,MATCH(D15,Estados!$A$2:$A$28,0)) -> 0.1640082 | G15: Paraná | H15: =INDEX(Estados!$W$2:$W$28,MATCH(G15,Estados!$A$2:$A$28,0)) -> 0.49149843 | J15: Santa Catarina | K15: =INDEX(Estados!$N$2:$N$28,MATCH(J15,Estados!$A$2:$A$28,0)) -> 0.2836
... A29: Minas Gerais | B29: =INDEX(Estados!$Q$2:$Q$28,MATCH(A29,Estados!$A$2:$A$28,0)) -> 666.93055 | D29: Mato Grosso do Sul | E29: =INDEX(Estados!$R$2:$R$28,MATCH(D29,Estados!$A$2:$A$28,0)) -> 0.11536786 | G29: Maranhão | H29: =INDEX(Estados!$W$2:$W$28,MATCH(G29,Estados!$A$2:$A$28,0)) -> 0.39200297 | J29: Espírito Santo | K29: =INDEX(Estados!$N$2:$N$28,MATCH(J29,Estados!$A$2:$A$28,0)) -> -0.0976
A30: Rio de Janeiro (estado) | B30: =INDEX(Estados!$Q$2:$Q$28,MATCH(A30,Estados!$A$2:$A$28,0)) -> 606.24371 | D30: Rio de Janeiro (estado) | E30: =INDEX(Estados!$R$2:$R$28,MATCH(D30,Estados!$A$2:$A$28,0)) -> 0.10386533 | J30: Mato Grosso | K30: =INDEX(Estados!$N$2:$N$28,MATCH(J30,Estados!$A$2:$A$28,0)) -> -0.1448

Sheet Gráficos
B1: Gráficos dos 27 estados (barra azul = Rio de Janeiro; cinza = os demais). Dados em 'Dados dos gráficos'.

Sheet Legenda
A1: Legenda e glossário
A3: 1. Siglas e termos
A4: Sigla ou termo | B4: Significado
A5: Siconfi | B5: Sistema de Informações Contábeis e Fiscais do Setor Público Brasileiro (Tesouro Nacional). Fonte de todos os números.
A6: RREO | B6: Relatório Resumido da Execução Orçamentária (bimestral). Usamos o 6º bimestre, que acumula o ano.
A7: RGF | B7: Relatório de Gestão Fiscal (quadrimestral; semestral nos municípios simplificados).
A8: LRF | B8: Lei de Responsabilidade Fiscal.
A9: RCL | B9: Receita corrente líquida: base dos limites de pessoal e de endividamento.
A10: RCL ajustada | B10: RCL menos transferências da União ligadas a emendas individuais, emendas de bancada e agentes comunitários de saúde. A dedução é feita pelo próprio ente no RGF.
A11: Empenhada | B11: Despesa comprometida no orçamento. Não é o mesmo que paga.
A12: Intra-orçamentárias | B12: Despesas entre órgãos do mesmo governo. Ficam de fora para não contar duas vezes.
A13: Restos a pagar | B13: Despesas empenhadas e não pagas até o fim do ano.
A14: Poder | B14: Executivo, Legislativo, Judiciário, Ministério Público ou Defensoria. A LRF fixa limite de pessoal para cada um.
A15: Dívida consolidada líquida | B15: Dívida consolidada menos as disponibilidades de caixa e haveres, segundo o RGF.
... A20: Mediana | B20: Valor do meio quando os entes são ordenados. Pouco sensível a casos extremos.
A22: 2. Colunas das abas Estados e Municípios RJ
A23: Aba | B23: Coluna | C23: O que é | D23: De onde vem
A24: Estados | B24: Ente | C24: Nome do ente | D24: Cadastro do Siconfi (`/entes`)
A25: Estados | B25: Código IBGE | C25: Código IBGE (2 dígitos para estado, 7 para município) | D25: Cadastro do Siconfi
A26: Estados | B26: População | C26: População do ente, estimativa 2024 do IBGE | D26: IBGE, SIDRA, tabela 6579, variável 9324
A27: Estados | B27: Receita realizada (R$) | C27: Receita realizada no ano, sem intra-orçamentárias | D27: RREO Anexo 01, ReceitasExcetoIntraOrcamentarias, 'Até o Bimestre (c)'
A28: Estados | B28: Despesa empenhada, Anexo 01 (R$) | C28: Despesa empenhada no ano, sem intra-orçamentárias | D28: RREO Anexo 01, DespesasExcetoIntraOrcamentarias, 'Despesas empenhadas até o bimestre (f)'
A29: Estados | B29: Despesa total, Anexo 02 (R$) | C29: Total de despesa do Anexo 02, sem intra-orçamentárias (em Armação dos Búzios, o Anexo 02 é incoerente e vale o total do Anexo 01) | D29: RREO Anexo 02, linha 'DESPESAS (EXCETO INTRA-ORÇAMENTÁRIAS) (I)'; Búzios: Anexo 01
A30: Estados | B30: Despesa em Saúde (R$) | C30: Despesa empenhada na função Saúde, sem intra-orçamentárias | D30: RREO Anexo 02, linha 'Saúde', 'Despesas empenhadas até o bimestre (b)'; Armação dos Búzios: DCA Anexo I-E, função 10 (checagem A2)
A31: Estados | B31: RCL ajustada (R$) | C31: Receita corrente líquida ajustada, base dos limites de pessoal | D31: RGF Anexo 01, ReceitaCorrenteLiquidaAjustada, 'Valor'
A32: Estados | B32: Pessoal Executivo (R$) | C32: Despesa total com pessoal do Executivo | D32: RGF Anexo 01, conta DespesaComPessoalTotal, coluna 'Valor'
A33: Estados | B33: Pessoal Legislativo (R$) | C33: Despesa total com pessoal do Legislativo | D33: RGF Anexo 01, conta DespesaComPessoalTotal, coluna 'Valor'
A34: Estados | B34: Pessoal Judiciário (R$) | C34: Despesa total com pessoal do Judiciário | D34: RGF Anexo 01, conta DespesaComPessoalTotal, coluna 'Valor'
... A83: Municípios RJ | B83: Observações | C83: Avisos sobre o ente | D83: Notebook da EDA
A85: 3. Limites desta análise
A86: • Um ano só (2024), e só o último período de cada relatório.
A87: • Os valores são o que cada ente declarou. Não foram auditados.
A88: • Limites de pessoal e de dívida são os declarados pelos entes, não conferidos com a lei.
A89: • O Siconfi mostra gasto, não a qualidade do atendimento. Nenhum indicador aqui mede se a saúde de um lugar é boa ou ruim.
A90: • O mínimo legal de saúde não está nesta planilha (fonte alternativa, o SIOPS, estava fora do ar em 21/10/2026).
A91: • Comparações valem dentro de cada grupo: estados entre si, municípios entre si.
A92: • Dados de 4 municípios estão marcados em amarelo por serem atípicos (RCL atípica ou totais de despesa inconsistentes). Estão mantidos, e a aba 'Com e sem' mostra o resultado sem eles.
